Workbook

Sheet Daybook
B1: Daybook
B4: Balance Sheet | G4: Income Statement
B5: Date | C5: Account | D5: Debit | E5: Credit | G5: Date | H5: Account | I5: Debit | J5: Credit
B6: 1 Jun 2015 | C6: Equity | E6: 3000 | G6: 26 Jun 2015 | H6: Cost of goods sold | I6: 400
B7: 1 Jun 2015 | C7: Cash | D7: 3000 | G7: 26 Jun 2015 | H7: Revenue | J7: 1200
B8: 10 Jun 2015 | C8: PP&E | D8: 1000 | G8: 26 Jun 2015 | H8: Utilitiy expenses | I8: 150
B9: 10 Jun 2015 | C9: Cash | E9: 1000 | G9: 20 Aug 2015 | H9: Revenue | J9: 2700
B10: 12 Jun 2015 | C10: Raw materials | D10: 500 | G10: 20 Aug 2015 | H10: Cost of goods sold | I10: 900
B11: 12 Jun 2015 | C11: Cash | E11: 250 | G11: 20 Aug 2015 | H11: Utilitiy expenses | I11: 200
B12: 12 Jun 2015 | C12: Trade payables | E12: 250 | G12: 20 Aug 2015 | H12: Depreciation | I12: 100
B13: 26 Jun 2015 | C13: Raw materials | E13: 400
B14: 26 Jun 2015 | C14: Cash | D14: 1200
B15: 26 Jun 2015 | C15: Cash | E15: 150
B16: 15 Jun 2015 | C16: Raw materials | D16: 900
B17: 15 Jun 2015 | C17: Cash | E17: 900
B18: 20 Aug 2015 | C18: Cash | D18: 2700
B19: 20 Aug 2015 | C19: Raw materials | E19: 900
B20: 20 Aug 2015 | C20: Cash | E20: 200
B21: 20 Aug 2015 | C21: PP&E | E21: 100

Sheet T-accounts
B1: T-accounts
B3: Balance Sheet | K3: Income Statement
B4: Assets | H4: Liabilities & Equity | K4: Expenses | R4: Income
C6: Cash | G6: Equity | L6: Cost of goods sold | P6: Revenue
C7: 3000 | D7: 1000 | H7: 3000 | L7: 400 | Q7: 1200
C8: 1200 | D8: 250 | L8: 900 | Q8: 2700
C9: 2700 | D9: 150
D10: 900 | G10: 0 | H10: =H7 -> 3000 | L10: =SUM(L7:L8) -> 1300 | M10: 0 | P10: 0 | Q10: =SUM(Q7:Q8) -> 3900
D11: 200 | G11: Total Cash | H11: =H10-G10 -> 3000 | L11: Total Cash | M11: =L10-M10 -> 1300 | P11: Total Cash | Q11: =Q10-P10 -> 3900
C12: =SUM(C7:C9) -> 6900 | D12: =SUM(D7:D11) -> 2500
C13: Total Cash | D13: =C12-D12 -> 4400 | G13: Trade payables | L13: Utility expenses
H14: 250 | L14: 150
C15: PP&E | L15: 200
C16: 1000 | D16: 100
G17: 0 | H17: =H14 -> 250 | L17: =SUM(L14:L15) -> 350 | M17: 0
G18: Total Cash | H18: =H17-G17 -> 250 | L18: Total Cash | M18: =L17-M17 -> 350
C19: =C16 -> 1000 | D19: =D16 -> 100
C20: Total Cash | D20: =C19-D19 -> 900 | L20: Depreciation
L21: 100
C22: Raw materials
C23: 500 | D23: 400
C24: 900 | D24: 900 | L24: =SUM(L21:L22) -> 100 | M24: 0
L25: Total Cash | M25: =L24-M24 -> 100
C26: =SUM(C23:C24) -> 1400 | D26: =SUM(D23:D24) -> 1300
C27: Total Cash | D27: =C26-D26 -> 100

Sheet Balance Sheet
B1: Balance Sheet
C3: As of 20th August 2015
C4: Assets | E4: Liabilities & Equity
C5: Cash | D5: ='T-accounts'!D13 -> 4400 | E5: Trade payable | F5: ='T-accounts'!H18 -> 250
C6: PP&E | D6: ='T-accounts'!D20 -> 900
C7: Raw materials | D7: ='T-accounts'!D27 -> 100 | E7: Equity | F7: ='T-accounts'!H11+'Income Statement'!C10 -> 5150
C8: Total assets | D8: =SUM(D5:D7) -> 5400 | E8: Total Liabilities | F8: =SUM(F5:F7) -> 5400

Sheet Income Statement
B1: Income Statement
B4: Income Statement | C4: FY15
B5: Revenues | C5: ='T-accounts'!Q11 -> 3900
B6: Costs of goods sold | C6: =-'T-accounts'!M11 -> -1300
B7: Gross profit | C7: =SUM(C5:C6) -> 2600
B8: Utility expenses | C8: =-'T-accounts'!M18 -> -350
B9: D&A | C9: =-'T-accounts'!M25 -> -100
B10: Net Income | C10: =SUM(C7:C9) -> 2150
