Workbook

Sheet Database
B1: Database
B4: Month | C4: Year | D4: Date | E4: Country | F4: Revenue | G4: Cogs | H4: Advertising Spend | I4: Staff costs | J4: Headcount | K4: Employee engagement | L4: Website traffic
B5: 1 | C5: 2019 | D5: =EOMONTH(DATE(C5,B5,"1"),0) -> 43496 | E5: USA | F5: 1801.8462 | G5: -602.76923 | H5: -317.56003 | I5: -252.92308 | J5: 125.53846 | K5: 3.808359 | L5: 69.025004
B6: 2 | C6: 2019 | D6: =EOMONTH(DATE(C6,B6,"1"),0) -> 43524 | E6: USA | F6: 1705.1922 | G6: -497.53846 | H6: -316.66868 | I6: -259.38462 | J6: 136.61538 | K6: 3.6003394 | L6: 57.520837
B7: 3 | C7: 2019 | D7: =EOMONTH(DATE(C7,B7,"1"),0) -> 43555 | E7: USA | F7: 2013.2308 | G7: -602.76923 | H7: -318.15532 | I7: -277.84615 | J7: 146.76923 | K7: 3.1106932 | L7: 60.851039
B8: 4 | C8: 2019 | D8: =EOMONTH(DATE(C8,B8,"1"),0) -> 43585 | E8: USA | F8: 1908.7038 | G8: -556.61538 | H8: -323.66212 | I8: -294.46154 | J8: 154.15385 | K8: 3.9171692 | L8: 64.960982
B9: 5 | C9: 2019 | D9: =EOMONTH(DATE(C9,B9,"1"),0) -> 43616 | E9: USA | F9: 2069.0769 | G9: -557.53846 | H9: -350.61672 | I9: -298.15385 | J9: 156.92308 | K9: 3.9171692 | L9: 64.960982
B10: 6 | C10: 2019 | D10: =EOMONTH(DATE(C10,B10,"1"),0) -> 43646 | E10: USA | F10: 2093.0769 | G10: -509.53846 | H10: -349.06432 | I10: -308.30769 | J10: 160.61538 | K10: 3.9171692 | L10: 71.706858
B11: 7 | C11: 2019 | D11: =EOMONTH(DATE(C11,B11,"1"),0) -> 43677 | E11: USA | F11: 2299.3846 | G11: -475.38462 | H11: -306.58462 | I11: -334.15385 | J11: 159.69231 | K11: 3.9171692 | L11: 71.706858
B12: 8 | C12: 2019 | D12: =EOMONTH(DATE(C12,B12,"1"),0) -> 43708 | E12: USA | F12: 1311.8162 | G12: -387.69231 | H12: 0 | I12: -309.23077 | J12: 156.92308 | K12: 3.9171692 | L12: 71.706858
B13: 9 | C13: 2019 | D13: =EOMONTH(DATE(C13,B13,"1"),0) -> 43738 | E13: USA | F13: 2004.9231 | G13: -510.46154 | H13: -336.17902 | I13: -258.46154 | J13: 170.76923 | K13: 3.9171692 | L13: 71.706858
B14: 10 | C14: 2019 | D14: =EOMONTH(DATE(C14,B14,"1"),0) -> 43769 | E14: USA | F14: 2302.1538 | G14: -534.46154 | H14: -430.54809 | I14: -331.38462 | J14: 179.07692 | K14: 3.9171692 | L14: 68.706787
B15: 11 | C15: 2019 | D15: =EOMONTH(DATE(C15,B15,"1"),0) -> 43799 | E15: USA | F15: 1940.0013 | G15: -441.23077 | H15: -142.21038 | I15: -339.69231 | J15: 180 | K15: 3.9171692 | L15: 68.706787
B16: 12 | C16: 2019 | D16: =EOMONTH(DATE(C16,B16,"1"),0) -> 43830 | E16: USA | F16: 2205.0831 | G16: -363.69231 | H16: -216.85185 | I16: -426.46154 | J16: 185.53846 | K16: 3.9171692 | L16: 68.706787
... B148: 12 | C148: 2021 | D148: =EOMONTH(DATE(C148,B148,"1"),0) -> 44561 | E148: Brazil | F148: 167.06234 | G148: -113.60239 | H148: -3.4382859 | I148: -11.194615 | J148: 12.6 | K148: 3.3769336 | L148: 12.591977

Sheet Analysis -->
B15: Analysis -->

Sheet 1. Trend analysis
B1: 1. Trend analysis
B4: in $ | C4: 43496 | D4: 43524 | E4: 43555 | F4: 43585 | G4: 43616 | H4: 43646 | I4: 43677 | J4: 43708 | K4: 43738 | L4: 43769 | M4: 43799 | N4: 43830 | P4: 43861 | Q4: 43890 | R4: 43921 | S4: 43951 | T4: 43982 | U4: 44012 | V4: 44043 | W4: 44074 | X4: 44104 | Y4: 44135 | Z4: 44165 | AA4: 44196 | AC4: 44227 | AD4: 44255 | AE4: 44286 | AF4: 44316 | AG4: 44347 | AH4: 44377 | AI4: 44408 | AJ4: 44439 | AK4: 44469 | AL4: 44500 | AM4: 44530 | AN4: 44561
B5: Revenue | C5: =SUMIF(Database!$D:$D,'1. Trend analysis'!C$4,Database!$F:$F) -> 1941.2308 | D5: =SUMIF(Database!$D:$D,'1. Trend analysis'!D$4,Database!$F:$F) -> 1849.4691 | E5: =SUMIF(Database!$D:$D,'1. Trend analysis'!E$4,Database!$F:$F) -> 2175.2769 | F5: =SUMIF(Database!$D:$D,'1. Trend analysis'!F$4,Database!$F:$F) -> 2080.8115 | G5: =SUMIF(Database!$D:$D,'1. Trend analysis'!G$4,Database!$F:$F) -> 2249.1231 | H5: =SUMIF(Database!$D:$D,'1. Trend analysis'!H$4,Database!$F:$F) -> 2268.6 | I5: =SUMIF(Database!$D:$D,'1. Trend analysis'!I$4,Database!$F:$F) -> 2498.3077 | J5: =SUMIF(Database!$D:$D,'1. Trend analysis'!J$4,Database!$F:$F) -> 1462.7393 | ... N5: =SUMIF(Database!$D:$D,'1. Trend analysis'!N$4,Database!$F:$F) -> 2448.0831 | P5: =SUMIF(Database!$D:$D,'1. Trend analysis'!P$4,Database!$F:$F) -> 2660.0985 | Q5: =SUMIF(Database!$D:$D,'1. Trend analysis'!Q$4,Database!$F:$F) -> 2301.8206 | R5: =SUMIF(Database!$D:$D,'1. Trend analysis'!R$4,Database!$F:$F) -> 2545.2376 | S5: =SUMIF(Database!$D:$D,'1. Trend analysis'!S$4,Database!$F:$F) -> 2850.2724 | T5: =SUMIF(Database!$D:$D,'1. Trend analysis'!T$4,Database!$F:$F) -> 3038.431 | U5: =SUMIF(Database!$D:$D,'1. Trend analysis'!U$4,Database!$F:$F) -> 3081.4458 | V5: =SUMIF(Database!$D:$D,'1. Trend analysis'!V$4,Database!$F:$F) -> 3239.2991 | W5: =SUMIF(Database!$D:$D,'1. Trend analysis'!W$4,Database!$F:$F) -> 1844.6119 | ... AA5: =SUMIF(Database!$D:$D,'1. Trend analysis'!AA$4,Database!$F:$F) -> 2853.372 | AC5: =SUMIF(Database!$D:$D,'1. Trend analysis'!AC$4,Database!$F:$F) -> 3363.3853 | AD5: =SUMIF(Database!$D:$D,'1. Trend analysis'!AD$4,Database!$F:$F) -> 2896.4021 | AE5: =SUMIF(Database!$D:$D,'1. Trend analysis'!AE$4,Database!$F:$F) -> 3365.8793 | AF5: =SUMIF(Database!$D:$D,'1. Trend analysis'!AF$4,Database!$F:$F) -> 3715.4704 | AG5: =SUMIF(Database!$D:$D,'1. Trend analysis'!AG$4,Database!$F:$F) -> 4039.0341 | AH5: =SUMIF(Database!$D:$D,'1. Trend analysis'!AH$4,Database!$F:$F) -> 3971.8638 | AI5: =SUMIF(Database!$D:$D,'1. Trend analysis'!AI$4,Database!$F:$F) -> 4245.9216 | AJ5: =SUMIF(Database!$D:$D,'1. Trend analysis'!AJ$4,Database!$F:$F) -> 2486.2807 | ... AN5: =SUMIF(Database!$D:$D,'1. Trend analysis'!AN$4,Database!$F:$F) -> 3799.3904
B6: Cogs | C6: =-SUMIF(Database!$D:$D,'1. Trend analysis'!C$4,Database!$G:$G) -> 706.15385 | D6: =-SUMIF(Database!$D:$D,'1. Trend analysis'!D$4,Database!$G:$G) -> 600 | E6: =-SUMIF(Database!$D:$D,'1. Trend analysis'!E$4,Database!$G:$G) -> 710.76923 | F6: =-SUMIF(Database!$D:$D,'1. Trend analysis'!F$4,Database!$G:$G) -> 656.30769 | G6: =-SUMIF(Database!$D:$D,'1. Trend analysis'!G$4,Database!$G:$G) -> 670.61538 | H6: =-SUMIF(Database!$D:$D,'1. Trend analysis'!H$4,Database!$G:$G) -> 593.53846 | I6: =-SUMIF(Database!$D:$D,'1. Trend analysis'!I$4,Database!$G:$G) -> 583.38462 | J6: =-SUMIF(Database!$D:$D,'1. Trend analysis'!J$4,Database!$G:$G) -> 474.46154 | ... N6: =-SUMIF(Database!$D:$D,'1. Trend analysis'!N$4,Database!$G:$G) -> 422.76923 | P6: =-SUMIF(Database!$D:$D,'1. Trend analysis'!P$4,Database!$G:$G) -> 596.71949 | Q6: =-SUMIF(Database!$D:$D,'1. Trend analysis'!Q$4,Database!$G:$G) -> 504.42901 | R6: =-SUMIF(Database!$D:$D,'1. Trend analysis'!R$4,Database!$G:$G) -> 596.36059 | S6: =-SUMIF(Database!$D:$D,'1. Trend analysis'!S$4,Database!$G:$G) -> 726.58171 | T6: =-SUMIF(Database!$D:$D,'1. Trend analysis'!T$4,Database!$G:$G) -> 705.03445 | U6: =-SUMIF(Database!$D:$D,'1. Trend analysis'!U$4,Database!$G:$G) -> 683.74814 | V6: =-SUMIF(Database!$D:$D,'1. Trend analysis'!V$4,Database!$G:$G) -> 612.10541 | W6: =-SUMIF(Database!$D:$D,'1. Trend analysis'!W$4,Database!$G:$G) -> 509.49499 | ... AA6: =-SUMIF(Database!$D:$D,'1. Trend analysis'!AA$4,Database!$G:$G) -> 589.98548 | AC6: =-SUMIF(Database!$D:$D,'1. Trend analysis'!AC$4,Database!$G:$G) -> 830.40526 | AD6: =-SUMIF(Database!$D:$D,'1. Trend analysis'!AD$4,Database!$G:$G) -> 681.69873 | AE6: =-SUMIF(Database!$D:$D,'1. Trend analysis'!AE$4,Database!$G:$G) -> 881.25704 | AF6: =-SUMIF(Database!$D:$D,'1. Trend analysis'!AF$4,Database!$G:$G) -> 962.7701 | AG6: =-SUMIF(Database!$D:$D,'1. Trend analysis'!AG$4,Database!$G:$G) -> 984.26686 | AH6: =-SUMIF(Database!$D:$D,'1. Trend analysis'!AH$4,Database!$G:$G) -> 892.57694 | AI6: =-SUMIF(Database!$D:$D,'1. Trend analysis'!AI$4,Database!$G:$G) -> 849.00259 | AJ6: =-SUMIF(Database!$D:$D,'1. Trend analysis'!AJ$4,Database!$G:$G) -> 651.03464 | ... AN6: =-SUMIF(Database!$D:$D,'1. Trend analysis'!AN$4,Database!$G:$G) -> 799.51581

Sheet 2. Comparative analysis
B1: 2. Comparative analysis
C3: 2020 | D3: 2020 | E3: 2020 | F3: 2020
B4: in $ | C4: USA | D4: Canada | E4: Mexico | F4: Brazil
B5: Revenue | C5: =SUMIFS(Database!$F:$F,Database!$C:$C,'2. Comparative analysis'!C$3,Database!$E:$E,'2. Comparative analysis'!C$4) -> 28425.843 | D5: =SUMIFS(Database!$F:$F,Database!$C:$C,'2. Comparative analysis'!D$3,Database!$E:$E,'2. Comparative analysis'!D$4) -> 1453.8325 | E5: =SUMIFS(Database!$F:$F,Database!$C:$C,'2. Comparative analysis'!E$3,Database!$E:$E,'2. Comparative analysis'!E$4) -> 2527.9539 | F5: =SUMIFS(Database!$F:$F,Database!$C:$C,'2. Comparative analysis'!F$3,Database!$E:$E,'2. Comparative analysis'!F$4) -> 1418.9779
B6: Cogs | C6: =SUMIFS(Database!$G:$G,Database!$C:$C,'2. Comparative analysis'!C$3,Database!$E:$E,'2. Comparative analysis'!C$4) -> -5741.806 | D6: =SUMIFS(Database!$G:$G,Database!$C:$C,'2. Comparative analysis'!D$3,Database!$E:$E,'2. Comparative analysis'!D$4) -> -365.53846 | E6: =SUMIFS(Database!$G:$G,Database!$C:$C,'2. Comparative analysis'!E$3,Database!$E:$E,'2. Comparative analysis'!E$4) -> -475.38462 | F6: =SUMIFS(Database!$G:$G,Database!$C:$C,'2. Comparative analysis'!F$3,Database!$E:$E,'2. Comparative analysis'!F$4) -> -980.51632
B7: Gross Profit | C7: =SUM(C5:C6) -> 22684.037 | D7: =SUM(D5:D6) -> 1088.2941 | E7: =SUM(E5:E6) -> 2052.5693 | F7: =SUM(F5:F6) -> 438.46154
B8: Gross Profit % | C8: =C7/C5 -> 0.79800754 | D8: =D7/D5 -> 0.74856907 | E8: =E7/E5 -> 0.81194886 | F8: =F7/F5 -> 0.30899816

Sheet 3. Value-based analysis
B1: 3.Value-based analysis
B4: in $ | C4: Scenario 1 | D4: Scenario 2 | E4: Scenario 3
B5: Volume | C5: =1.1*D5 -> 23256.063 | D5: 21141.875 | E5: =D5*0.85 -> 17970.594
B6: Price | C6: 1.4 | D6: 1.6 | E6: 1.8
B7: Revenue | C7: =C5*C6 -> 32558.488 | D7: =D5*D6 -> 33827 | E7: =E5*E6 -> 32347.069
B9: Cogs per unit | C9: -0.33 | D9: -0.35 | E9: -0.39
B10: Cogs | C10: =C5*C9 -> -7674.5006 | D10: =D5*D9 -> -7399.6562 | E10: =E5*E9 -> -7008.5316
B12: Gross Profit | C12: =C7+C10 -> 24883.987 | D12: =D7+D10 -> 26427.344 | E12: =E7+E10 -> 25338.537
