Workbook

Sheet Cover
B9: Tesla
B10: Company analysis

Sheet Drivers
B1: Drivers
B3: Selected case | C3: 2
B4: Company | C4: Tesla
B5: Currency | C5: USD
B6: Domestic country | C6: United States
B7: 10-year treasury yield (Sep 18 2020) | C7: 0.00697
B8: Market risk premium US | C8: 0.05
B9: Company beta (Dec 15 2020) | C9: 2.15
B10: Tesla share price (Dec 15 2020) | C10: 639.83
B11: Bond Yield (Sep 18 2020) | C11: 0.04324
B12: Corporate tax rate | C12: 0.21
B13: Expected inflation | C13: 0.02

Sheet Input -->
B14: Input -->

Sheet P&L Input
B1: P&L Input
B3: (in thousands) | C3: 2015 Act | D3: 2016 Act | E3: 2017 Act | F3: 2018 Act | G3: 2019 Act
B4: Automotive revenues | C4: 3740973 | D4: 6350766 | E4: 9641300 | F4: 18514983 | G4: 20821000
B5: Energy generation and storage | C5: 14477 | D5: 181394 | E5: 1116266 | F5: 1555244 | G5: 1531000
B6: Services and other | C6: 290575 | D6: 467972 | E6: 1001185 | F6: 1391041 | G6: 2226000
B7: Total revenues | C7: =SUM(C4:C6) -> 4046025 | D7: =SUM(D4:D6) -> 7000132 | E7: =SUM(E4:E6) -> 11758751 | F7: =SUM(F4:F6) -> 21461268 | G7: =SUM(G4:G6) -> 24578000
B8: Automotive cost of revenues | C8: -2823302 | D8: -4750081 | E8: -7432704 | F8: -14173997 | G8: -16398000
B9: Energy generation and storage cost of revenues | C9: -12287 | D9: -178332 | E9: -874538 | F9: -1364896 | G9: -1341000
B10: Services and other cost of revenues | C10: -286933 | D10: -472462 | E10: -1229022 | F10: -1880354 | G10: -2770000
B11: Gross profit | C11: =SUM(C7:C10) -> 923503 | D11: =SUM(D7:D10) -> 1599257 | E11: =SUM(E7:E10) -> 2222487 | F11: =SUM(F7:F10) -> 4042021 | G11: =SUM(G7:G10) -> 4069000
B12: Research and development | C12: -717900 | D12: -834408 | E12: -1378073 | F12: -1460370 | G12: -1343000
B13: Selling, general and administrative | C13: -922232 | D13: -1432189 | E13: -2476500 | F13: -2834491 | G13: -2646000
B14: Restructuring and other | F14: -135233 | G14: -149000
B15: EBIT | C15: =SUM(C11:C14) -> -716629 | D15: =SUM(D11:D14) -> -667340 | E15: =SUM(E11:E14) -> -1632086 | F15: =SUM(F11:F14) -> -388073 | G15: =SUM(G11:G14) -> -69000
B16: Interest income | C16: 1508 | D16: 8530 | E16: 19686 | F16: 24533 | G16: 44000
B17: Interest expense | C17: -118851 | D17: -198810 | E17: -471259 | F17: -663071 | G17: -685000
B18: Other income (expense), net | C18: -41652 | D18: 111272 | E18: -125373 | F18: 21866 | G18: 45000
B19: EBT | C19: =SUM(C15:C18) -> -875624 | D19: =SUM(D15:D18) -> -746348 | E19: =SUM(E15:E18) -> -2209032 | F19: =SUM(F15:F18) -> -1004745 | G19: =SUM(G15:G18) -> -665000
B20: Provision for income taxes | C20: -13039 | D20: -26698 | E20: -31546 | F20: -57837 | G20: -110000
B21: Net loss incl. minority interests | C21: =SUM(C19:C20) -> -888663 | D21: =SUM(D19:D20) -> -773046 | E21: =SUM(E19:E20) -> -2240578 | F21: =SUM(F19:F20) -> -1062582 | G21: =SUM(G19:G20) -> -775000
B22: Minority interests | C22: 0 | D22: 98132 | E22: 279178 | F22: 86491 | G22: -87000
B23: Net loss | C23: =SUM(C21:C22) -> -888663 | D23: =SUM(D21:D22) -> -674914 | E23: =SUM(E21:E22) -> -1961400 | F23: =SUM(F21:F22) -> -976091 | G23: =SUM(G21:G22) -> -862000
B25: KPIs
B26: Revenue % automotive y-o-y | D26: =D4/C4-1 -> 0.69762412 | E26: =E4/D4-1 -> 0.51813183 | F26: =F4/E4-1 -> 0.92038242 | G26: =G4/F4-1 -> 0.1245487
B27: Revenue % generation y-o-y | D27: =D5/C5-1 -> 11.529806 | E27: =E5/D5-1 -> 5.1538199 | F27: =F5/E5-1 -> 0.39325573 | G27: =G5/F5-1 -> -0.015588551
B28: Revenue % services y-o-y | D28: =D6/C6-1 -> 0.61050331 | E28: =E6/D6-1 -> 1.1394122 | F28: =F6/E6-1 -> 0.38939457 | G28: =G6/F6-1 -> 0.6002404
B29: GP% automotive | C29: =(C4+C8)/C4 -> 0.24530276 | D29: =(D4+D8)/D4 -> 0.25204597 | E29: =(E4+E8)/E4 -> 0.22907658 | F29: =(F4+F8)/F4 -> 0.23445801 | G29: =(G4+G8)/G4 -> 0.21242976
B30: GP% energy generation and automotive | C30: =(C5+C9)/C5 -> 0.15127444 | D30: =(D5+D9)/D5 -> 0.016880382 | E30: =(E5+E9)/E5 -> 0.21655054 | F30: =(F5+F9)/F5 -> 0.12239108 | G30: =(G5+G9)/G5 -> 0.12410189
B31: GP% services and other | C31: =(C6+C10)/C6 -> 0.012533769 | D31: =(D6+D10)/D6 -> -0.0095945911 | E31: =(E6+E10)/E6 -> -0.22756733 | F31: =(F6+F10)/F6 -> -0.3517603 | G31: =(G6+G10)/G6 -> -0.24438455
B32: Overall GP% | C32: =(SUM(C4:C6)+SUM(C8:C10))/SUM(C4:C6) -> 0.22824945 | D32: =(SUM(D4:D6)+SUM(D8:D10))/SUM(D4:D6) -> 0.22846098 | E32: =(SUM(E4:E6)+SUM(E8:E10))/SUM(E4:E6) -> 0.18900706 | F32: =(SUM(F4:F6)+SUM(F8:F10))/SUM(F4:F6) -> 0.18834027 | G32: =(SUM(G4:G6)+SUM(G8:G10))/SUM(G4:G6) -> 0.16555456
B33: EBIT % | C33: =C15/C7 -> -0.17711927 | D33: =D15/D7 -> -0.095332488 | E33: =E15/E7 -> -0.13879756 | F33: =F15/F7 -> -0.018082482 | G33: =G15/G7 -> -0.0028073887
B34: Net loss % | C34: =C23/C7 -> -0.21963853 | D34: =D23/D7 -> -0.096414468 | E34: =E23/E7 -> -0.16680343 | F34: =F23/F7 -> -0.045481516 | G34: =G23/G7 -> -0.035072016
B35: ROA | C35: =C23/'Balance Sheet Input'!C18 -> -0.11014746 | D35: =D23/'Balance Sheet Input'!D18 -> -0.029779021 | E35: =E23/'Balance Sheet Input'!E18 -> -0.068447899 | F35: =F23/'Balance Sheet Input'!F18 -> -0.03282124 | G35: =G23/'Balance Sheet Input'!G18 -> -0.025124603
B36: ROE | C36: =C23/'Balance Sheet Input'!C32 -> -0.82002373 | D36: =D23/'Balance Sheet Input'!D32 -> -0.14200013 | E36: =E23/'Balance Sheet Input'!E32 -> -0.46289544 | F36: =F23/'Balance Sheet Input'!F32 -> -0.1982618 | G36: =G23/'Balance Sheet Input'!G32 -> -0.13025083

Sheet Balance Sheet Input
B1: Balance Sheet Input
B3: (in thousands) | C3: 31 Dec 2015 | D3: 31 Dec 2016 | E3: 31 Dec 2017 | F3: 31 Dec 2018 | G3: 31 Dec 2019
B4: Cash and cash equivalents | C4: 1196908 | D4: 3393216 | E4: 3367914 | F4: 3685618 | G4: 6268000
B5: Restricted cash and marketable securities | C5: 22628 | D5: 105519 | E5: 155323 | F5: 192551 | G5: 246000
B6: Accounts receivable, net | C6: 168965 | D6: 499142 | E6: 515381 | F6: 949022 | G6: 1324000
B7: Inventory | C7: 1277838 | D7: 2067454 | E7: 2263537 | F7: 3113446 | G7: 3552000
B8: Prepaid expenses and other current assets | C8: 115667 | D8: 194465 | E8: 268365 | F8: 365671 | G8: 713000
B9: Total current assets | C9: =SUM(C4:C8) -> 2782006 | D9: =SUM(D4:D8) -> 6259796 | E9: =SUM(E4:E8) -> 6570520 | F9: =SUM(F4:F8) -> 8306308 | G9: =SUM(G4:G8) -> 12103000
B10: Operating lease vehicles, net | C10: 1791403 | D10: 3134080 | E10: 4116604 | F10: 2089758 | G10: 2447000
B11: Solar energy systems, leased and to be leased, net | C11: 0 | D11: 5919880 | E11: 6347490 | F11: 6271396 | G11: 6138000
B12: Property, plant and equipment, net | C12: 3403334 | D12: 5982957 | E12: 10027522 | F12: 11330077 | G12: 10396000
B13: Operating lease right-of-use assets | C13: 0 | D13: 0 | E13: 0 | F13: 0 | G13: 1218000
B14: Intangible assets, net | C14: 12816 | D14: 376145 | E14: 361502 | F14: 282492 | G14: 339000
B15: portion | C15: 0 | D15: 506302 | E15: =456652+60237 -> 516889 | F15: 489707 | G15: 591000
B16: Restricted cash, net of current portion | C16: 31522 | D16: 268165 | E16: 441722 | F16: 398219 | G16: 269000
B17: Other assets | C17: 46858 | D17: 216751 | E17: 273123 | F17: 571657 | G17: 808000
B18: Total assets | C18: =SUM(C9:C17) -> 8067939 | D18: =SUM(D9:D17) -> 22664076 | E18: =SUM(E9:E17) -> 28655372 | F18: =SUM(F9:F17) -> 29739614 | G18: =SUM(G9:G17) -> 34309000
B19: Accounts payable | C19: 916148 | D19: 1860341 | E19: 2390250 | F19: 3404451 | G19: 3771000
B20: Accrued liabilities | C20: 422798 | D20: 1210028 | E20: 1731366 | F20: 2094253 | G20: 2905000
B21: Deferred revenue | C21: 423961 | D21: 763126 | E21: 1015253 | F21: 630292 | G21: 1163000
B22: Resale value guarantees | C22: 136831 | D22: 179504 | E22: 787333 | F22: 502840 | G22: 317000
B23: Customer deposits | C23: 283370 | D23: 663859 | E23: 853919 | F23: 792601 | G23: 726000
B24: Current portion of long-term debt and capital leases | C24: 627927 | D24: 984211 | E24: 796549 | F24: 2567699 | G24: 1785000
B25: Current portion of solar bonds issued to related
B26: parties | C26: 0 | D26: 165936 | E26: 100000 | F26: 0 | G26: 0
B27: Total current liabilities | C27: 2811035 | D27: 5827005 | E27: =SUM(E19:E26) -> 7674670 | F27: =SUM(F19:F26) -> 9992136 | G27: =SUM(G19:G26) -> 10667000
B28: Long-term debt and capital leases, net of current
B29: portion | C29: 2021093 | D29: 5860049 | E29: 9415700 | F29: 9403672 | G29: 11634000
B30: Other liabilities | C30: 2152107 | D30: 5438936 | E30: 6330414 | F30: 4586166 | G30: 4541000
B31: Total liabilities | C31: =SUM(C27:C30) -> 6984235 | D31: =SUM(D27:D30) -> 17125990 | E31: =SUM(E27:E30) -> 23420784 | F31: =SUM(F27:F30) -> 23981974 | G31: =SUM(G27:G30) -> 26842000
B32: Total stockholders' equity | C32: 1083704 | D32: 4752911 | E32: 4237242 | F32: 4923243 | G32: 6618000
B33: Noncontrolling interests in subsidiaries | C33: 0 | D33: 785175 | E33: 997346 | F33: 834397 | G33: 849000
B34: Total liabilities and equity | C34: =C31+C32+C33 -> 8067939 | D34: =D31+D32+D33 -> 22664076 | E34: =E31+E32+E33 -> 28655372 | F34: =F31+F32+F33 -> 29739614 | G34: =G31+G32+G33 -> 34309000
B36: KPIs
B37: Liquidity ratios
B38: Quick ratio | C38: =(C4+C5)/C27 -> 0.43383878 | D38: =(D4+D5)/D27 -> 0.60043453 | E38: =(E4+E5)/E27 -> 0.45907342 | F38: =(F4+F5)/F27 -> 0.38812212 | G38: =(G4+G5)/G27 -> 0.61066842
B39: Current ratio | C39: =C9/C27 -> 0.9896732 | D39: =D9/D27 -> 1.0742733 | E39: =E9/E27 -> 0.85613062 | F39: =F9/F27 -> 0.83128452 | G39: =G9/G27 -> 1.1346208
B40: DSO | C40: =C6/'P&L Input'!C7*360 -> 15.033867 | D40: =D6/'P&L Input'!D7*360 -> 25.669676 | E40: =E6/'P&L Input'!E7*360 -> 15.778645 | F40: =F6/'P&L Input'!F7*360 -> 15.919279 | G40: =G6/'P&L Input'!G7*360 -> 19.392953
B41: DIO | C41: =-C7/SUM('P&L Input'!C8:C10)*360 -> 147.32376 | D41: =-D7/SUM('P&L Input'!D8:D10)*360 -> 137.80794 | E41: =-E7/SUM('P&L Input'!E8:E10)*360 -> 85.449954 | F41: =-F7/SUM('P&L Input'!F8:F10)*360 -> 64.344949 | G41: =-G7/SUM('P&L Input'!G8:G10)*360 -> 62.349213
B42: DPO | C42: =-C19/SUM('P&L Input'!C8:C10)*360 -> 105.62401 | D42: =-D19/SUM('P&L Input'!D8:D10)*360 -> 124.00264 | E42: =-E19/SUM('P&L Input'!E8:E10)*360 -> 90.23345 | F42: =-F19/SUM('P&L Input'!F8:F10)*360 -> 70.35909 | G42: =-G19/SUM('P&L Input'!G8:G10)*360 -> 66.193379
B43: Net Trading Cycle | C43: =C40+C41-C42 -> 56.733621 | D43: =D40+D41-D42 -> 39.474972 | E43: =E40+E41-E42 -> 10.995149 | F43: =F40+F41-F42 -> 9.9051388 | G43: =G40+G41-G42 -> 15.548787
B44: Solvency ratios
B45: Debt ratio | C45: =C31/C18 -> 0.86567772 | D45: =D31/D18 -> 0.75564475 | E45: =E31/E18 -> 0.81732612 | F45: =F31/F18 -> 0.80639829 | G45: =G31/G18 -> 0.78236031
B46: Interest coverage | C46: <0 | D46: <0 | E46: <0 | F46: <0 | G46: <0

Sheet Workings -->
B14: Workings -->

Sheet Income Statement items
B14: Income Statement items

Sheet Automotive
B14: Automotive

Sheet Deliveries
B1: Deliveries
C3: Tesla Deliveries
B4: Vehicle | C4: 2015 Act | D4: 2016 Act | E4: 2017 Act | F4: 2018 Act | G4: 2019 Act | H4: 2020 Fcst | I4: 2021 Fcst | J4: 2022 Fcst | K4: 2023 Fcst | L4: 2024 Fcst | M4: 2025 Fcst | N4: 2026 Fcst | O4: 2027 Fcst | P4: 2028 Fcst | Q4: 2029 Fcst
B5: Tesla Model 3 | C5: 0 | D5: 0 | E5: 1764 | F5: 146055 | G5: 300815 | H5: =G5*(1+H15) -> 481304 | I5: =H5*(1+I15) -> 529434.4 | J5: =I5*(1+J15) -> 582377.84 | K5: =J5*(1+K15) -> 628968.07 | L5: =K5*(1+L15) -> 679285.51 | M5: =L5*(1+M15) -> 706456.93 | N5: =M5*(1+N15) -> 734715.21 | O5: =N5*(1+O15) -> 764103.82 | ... Q5: =P5*(1+Q15) -> 826454.69
B6: Tesla Model S and X | C6: 50580 | D6: 76230 | E6: 101312 | F6: 98865 | G6: 66385 | H6: =G6*(1+H16) -> 69040.4 | I6: =H6*(1+I16) -> 71802.016 | J6: =I6*(1+J16) -> 74674.097 | K6: =J6*(1+K16) -> 77661.061 | L6: =K6*(1+L16) -> 80767.503 | M6: =L6*(1+M16) -> 83998.203 | N6: =M6*(1+N16) -> 87358.131 | O6: =N6*(1+O16) -> 90852.456 | ... Q6: =P6*(1+Q16) -> 98266.017
B7: Tesla Model Y | C7: 0 | D7: 0 | E7: 0 | F7: 0 | G7: 0 | H7: =E5 -> 1764 | I7: =H7*(1+I17) -> 146055 | J7: =I7*(1+J17) -> 300815 | K7: =J7*(1+K17) -> 481304 | L7: =K7*(1+L17) -> 529434.4 | M7: =L7*(1+M17) -> 582377.84 | N7: =M7*(1+N17) -> 628968.07 | O7: =N7*(1+O17) -> 679285.51 | P7: =O7*(1+P17) -> 706456.93 | Q7: =P7*(1+Q17) -> 734715.21
B8: Tesla Roadster 2 | C8: 0 | D8: 0 | E8: 0 | F8: 0 | G8: 0 | H8: 0 | I8: 0 | J8: 500 | K8: =J8*(1+K18) -> 1000 | L8: =K8*(1+L18) -> 1500 | M8: =L8*(1+M18) -> 1650 | N8: =M8*(1+N18) -> 1815 | O8: =N8*(1+O18) -> 1960.2 | P8: =O8*(1+P18) -> 2117.016 | Q8: =P8*(1+Q18) -> 2201.6966
B9: Tesla Pickup | C9: 0 | D9: 0 | E9: 0 | F9: 0 | G9: 0 | H9: 0 | I9: 250 | J9: =I9*(1+J19) -> 20699.405 | K9: =J9*(1+K19) -> 42632.511 | L9: =K9*(1+L19) -> 68212.018 | M9: =L9*(1+M19) -> 75033.22 | N9: =M9*(1+N19) -> 82536.542 | O9: =N9*(1+O19) -> 89139.465 | P9: =O9*(1+P19) -> 96270.623 | Q9: =P9*(1+Q19) -> 100121.45
B10: Tesla Semi | C10: 0 | D10: 0 | E10: 0 | F10: 0 | G10: 0 | H10: 0 | I10: 250 | J10: =I10*(1+J20) -> 20699.405 | K10: =J10*(1+K20) -> 42632.511 | L10: =K10*(1+L20) -> 68212.018 | M10: =L10*(1+M20) -> 75033.22 | N10: =M10*(1+N20) -> 82536.542 | O10: =N10*(1+O20) -> 89139.465 | P10: =O10*(1+P20) -> 96270.623 | Q10: =P10*(1+Q20) -> 100121.45
B11: Total | C11: =SUM(C5:C10) -> 50580 | D11: =SUM(D5:D10) -> 76230 | E11: =SUM(E5:E10) -> 103076 | F11: =SUM(F5:F10) -> 244920 | G11: =SUM(G5:G10) -> 367200 | H11: =SUM(H5:H10) -> 552108.4 | I11: =SUM(I5:I10) -> 747791.42 | J11: =SUM(J5:J10) -> 999765.75 | ... Q11: =SUM(Q5:Q10) -> 1861880.5
B13: y-o-y growth %
B15: Tesla Model 3 | C15: n.a. | D15: n.a. | E15: n.a. | F15: =F5/E5-1 -> 81.797619 | G15: =G5/F5-1 -> 1.0596008 | H15: 0.6 | I15: =$C$25 -> 0.1 | J15: =$C$25 -> 0.1 | K15: =$C$26 -> 0.08 | L15: =$C$26 -> 0.08 | M15: =$C$27 -> 0.04 | N15: =$C$27 -> 0.04 | O15: =$C$27 -> 0.04 | P15: =$C$27 -> 0.04 | Q15: =$C$27 -> 0.04
B16: Tesla Model S and X | C16: n.a. | D16: =D6/C6-1 -> 0.50711744 | E16: =E6/D6-1 -> 0.32903057 | F16: =F6/E6-1 -> -0.024153111 | G16: =G6/F6-1 -> -0.3285288 | H16: =$C$27 -> 0.04 | I16: =$C$27 -> 0.04 | J16: =$C$27 -> 0.04 | K16: =$C$27 -> 0.04 | L16: =$C$27 -> 0.04 | M16: =$C$27 -> 0.04 | N16: =$C$27 -> 0.04 | O16: =$C$27 -> 0.04 | ... Q16: =$C$27 -> 0.04
B17: Tesla Model Y | C17: n.a. | D17: n.a. | E17: n.a. | F17: n.a. | G17: n.a. | H17: n.a. | I17: =F15 -> 81.797619 | J17: =G15 -> 1.0596008 | K17: =H15 -> 0.6 | L17: =I15 -> 0.1 | M17: =J15 -> 0.1 | N17: =K15 -> 0.08 | O17: =L15 -> 0.08 | P17: =M15 -> 0.04 | Q17: =N15 -> 0.04
B18: Tesla Roadster 2 | C18: n.a. | D18: n.a. | E18: n.a. | F18: n.a. | G18: n.a. | H18: n.a. | I18: n.a. | J18: n.a. | K18: 1 | L18: 0.5 | M18: =$C$25 -> 0.1 | N18: =$C$25 -> 0.1 | O18: =$C$26 -> 0.08 | P18: =$C$26 -> 0.08 | Q18: =$C$27 -> 0.04
B19: Tesla Pickup | C19: n.a. | D19: n.a. | E19: n.a. | F19: n.a. | G19: n.a. | H19: n.a. | I19: n.a. | J19: =F$15 -> 81.797619 | K19: =G$15 -> 1.0596008 | L19: =H$15 -> 0.6 | M19: =$C$25 -> 0.1 | N19: =$C$25 -> 0.1 | O19: =$C$26 -> 0.08 | P19: =$C$26 -> 0.08 | Q19: =$C$27 -> 0.04
B20: Tesla Semi | C20: n.a. | D20: n.a. | E20: n.a. | F20: n.a. | G20: n.a. | H20: n.a. | I20: n.a. | J20: =F$15 -> 81.797619 | K20: =G$15 -> 1.0596008 | L20: =H$15 -> 0.6 | M20: =$C$25 -> 0.1 | N20: =$C$25 -> 0.1 | O20: =$C$26 -> 0.08 | P20: =$C$26 -> 0.08 | Q20: =$C$27 -> 0.04
B24: Assumed growth after introduction:
B25: 2 years | C25: 0.1
B26: 2 years | C26: 0.08
B27: onwards | C27: 0.04

Sheet Deliveries development

Sheet Deliveries comparables
B1: Deliveries comparables
B3: Comparables 2015-2019
B6: Vehicle Sales 2015-2019 - average | C6: Average | D6: Adj. Average
B7: GM | C7: 9600340 | D7: =C7 -> 9600340
B8: Ford | C8: 6607000 | D8: =C8 -> 6607000
B9: Fiat Chrysler | C9: 4740000 | D9: =C9 -> 4740000
B10: BMW | C10: 2460000 | D10: =C10 -> 2460000
B11: Volkswagen | C11: 10700000 | D11: =C11 -> 10700000
B12: Jaguar | C12: n.a. | D12: n.a.
B13: Porsche | C13: n.a. | D13: n.a.
B14: Ferrari | C14: n.a. | D14: n.a.
B15: Scania | C15: n.a. | D15: n.a.
B16: MAN | C16: n.a. | D16: n.a.
B17: Paccar | C17: n.a. | D17: n.a.
B18: Average | C18: n.a. | D18: =AVERAGE(D7:D17) -> 6821468
B22: Tesla Expected Deliveries
B23: 2020 | D23: =Deliveries!H$11 -> 552108.4
B24: 2024 | D24: =Deliveries!L$11 -> 1427411.5
B25: 2029 | D25: =Deliveries!Q$11 -> 1861880.5

Sheet Average Prices
B1: Average prices
B3: Model and Version | C3: Range | D3: Base price | E3: Fully loaded | F3: Average Price per Model
B4: Model 3 Standard Range Plus | C4: 250 miles | D4: 39990 | E4: 51490
B5: Model 3 Long Range | C5: 322 miles | D5: 48990 | E5: 60490
B6: Model 3 Performance | C6: 322 miles | D6: 56990 | E6: 66990
B7: Average Model 3 | F7: =AVERAGE(D4:E6) -> 54156.667
B8: Model S Long Range | C8: 373 miles | D8: 79990 | E8: 95490
B9: Model S Performance | C9: 348 miles | D9: 99990 | E9: 115990
B10: Model X Long Range | C10: 328 miles | D10: 84990 | E10: 106490
B11: Model X Performance | C11: 305 miles | D11: 104990 | E11: 128490
B12: Average Model S and X | F12: =AVERAGE(D8:E11) -> 102052.5
B14: Model | C14: Base price | D14: Max price
B15: CyberTruck | C15: 39900 | D15: 76900 | F15: =AVERAGE(C15:D15) -> 58400
B16: Model Y | C16: 48000 | D16: 74000 | F16: =AVERAGE(C16:D16) -> 61000
B17: Roadster 2020 | C17: 200000 | D17: 250000 | F17: =AVERAGE(C17:D17) -> 225000
B18: Semi | C18: 150000 | D18: 200000 | F18: =AVERAGE(C18:D18) -> 175000

Sheet Revenue automotive
B1: Revenue Automotive
C3: Tesla Revenue Automotive (in mln $)
B4: Vehicle | C4: 2015 Act | D4: 2016 Act | E4: 2017 Act | F4: 2018 Act | G4: 2019 Act | H4: 2020 Fcst | I4: 2021 Fcst | J4: 2022 Fcst | K4: 2023 Fcst | L4: 2024 Fcst | M4: 2025 Fcst | N4: 2026 Fcst | O4: 2027 Fcst | P4: 2028 Fcst | Q4: 2029 Fcst | R4: Average Price ($)
B5: Tesla Model 3 | E5: 88.268789 | F5: 8136.483 | G5: 14705.599 | H5: =($R5*Deliveries!H5)*H14/1000000 -> 26065.82 | I5: =($R5*Deliveries!I5)*I14/1000000 -> 28672.402 | J5: =($R5*Deliveries!J5)*J14/1000000 -> 31539.643 | K5: =($R5*Deliveries!K5)*K14/1000000 -> 34062.814 | L5: =($R5*Deliveries!L5)*L14/1000000 -> 36787.839 | M5: =($R5*Deliveries!M5)*M14/1000000 -> 38259.353 | N5: =($R5*Deliveries!N5)*N14/1000000 -> 39789.727 | O5: =($R5*Deliveries!O5)*O14/1000000 -> 41381.316 | ... Q5: =($R5*Deliveries!Q5)*Q14/1000000 -> 44758.031 | R5: =AVERAGE('Average Prices'!D4:E6) -> 54156.667
B6: Tesla Model S and X | C6: 3740.973 | D6: 6350.766 | E6: 9553.0312 | F6: 10378.5 | G6: 6115.4007 | H6: =($R6*Deliveries!H6)*H15/1000000 -> 7045.7454 | I6: =($R6*Deliveries!I6)*I15/1000000 -> 7327.5752 | J6: =($R6*Deliveries!J6)*J15/1000000 -> 7620.6782 | K6: =($R6*Deliveries!K6)*K15/1000000 -> 7925.5054 | L6: =($R6*Deliveries!L6)*L15/1000000 -> 8242.5256 | M6: =($R6*Deliveries!M6)*M15/1000000 -> 8572.2266 | N6: =($R6*Deliveries!N6)*N15/1000000 -> 8915.1157 | O6: =($R6*Deliveries!O6)*O15/1000000 -> 9271.7203 | ... Q6: =($R6*Deliveries!Q6)*Q15/1000000 -> 10028.293 | R6: =AVERAGE('Average Prices'!D8:E11) -> 102052.5
B7: Tesla Model Y | C7: =($R7*Deliveries!C7)/1000000 -> 0 | D7: =($R7*Deliveries!D7)/1000000 -> 0 | E7: =($R7*Deliveries!E7)/1000000 -> 0 | F7: =($R7*Deliveries!F7)/1000000 -> 0 | G7: =($R7*Deliveries!G7)/1000000 -> 0 | H7: =($R7*Deliveries!H7)*H16/1000000 -> 107.604 | I7: =($R7*Deliveries!I7)*I16/1000000 -> 8909.355 | J7: =($R7*Deliveries!J7)*J16/1000000 -> 18349.715 | K7: =($R7*Deliveries!K7)*K16/1000000 -> 29359.544 | L7: =($R7*Deliveries!L7)*L16/1000000 -> 32295.498 | M7: =($R7*Deliveries!M7)*M16/1000000 -> 35525.048 | N7: =($R7*Deliveries!N7)*N16/1000000 -> 38367.052 | O7: =($R7*Deliveries!O7)*O16/1000000 -> 41436.416 | ... Q7: =($R7*Deliveries!Q7)*Q16/1000000 -> 44817.628 | R7: =AVERAGE('Average Prices'!C16:D16) -> 61000
B8: Tesla Roadster 2 | C8: =($R8*Deliveries!C8)/1000000 -> 0 | D8: =($R8*Deliveries!D8)/1000000 -> 0 | E8: =($R8*Deliveries!E8)/1000000 -> 0 | F8: =($R8*Deliveries!F8)/1000000 -> 0 | G8: =($R8*Deliveries!G8)/1000000 -> 0 | H8: =($R8*Deliveries!H8)*H17/1000000 -> 0 | I8: =($R8*Deliveries!I8)*I17/1000000 -> 0 | J8: =($R8*Deliveries!J8)*J17/1000000 -> 112.5 | K8: =($R8*Deliveries!K8)*K17/1000000 -> 225 | L8: =($R8*Deliveries!L8)*L17/1000000 -> 337.5 | M8: =($R8*Deliveries!M8)*M17/1000000 -> 371.25 | N8: =($R8*Deliveries!N8)*N17/1000000 -> 408.375 | O8: =($R8*Deliveries!O8)*O17/1000000 -> 441.045 | ... Q8: =($R8*Deliveries!Q8)*Q17/1000000 -> 495.38174 | R8: =AVERAGE('Average Prices'!C17:D17) -> 225000
B9: Tesla Pickup | C9: =($R9*Deliveries!C9)/1000000 -> 0 | D9: =($R9*Deliveries!D9)/1000000 -> 0 | E9: =($R9*Deliveries!E9)/1000000 -> 0 | F9: =($R9*Deliveries!F9)/1000000 -> 0 | G9: =($R9*Deliveries!G9)/1000000 -> 0 | H9: =($R9*Deliveries!H9)*H18/1000000 -> 0 | I9: =($R9*Deliveries!I9)*I18/1000000 -> 14.6 | J9: =($R9*Deliveries!J9)*J18/1000000 -> 1208.8452 | K9: =($R9*Deliveries!K9)*K18/1000000 -> 2489.7387 | L9: =($R9*Deliveries!L9)*L18/1000000 -> 3983.5819 | M9: =($R9*Deliveries!M9)*M18/1000000 -> 4381.94 | N9: =($R9*Deliveries!N9)*N18/1000000 -> 4820.134 | O9: =($R9*Deliveries!O9)*O18/1000000 -> 5205.7448 | ... Q9: =($R9*Deliveries!Q9)*Q18/1000000 -> 5847.0925 | R9: =AVERAGE('Average Prices'!C15:D15) -> 58400
B10: Tesla Semi | C10: =($R10*Deliveries!C10)/1000000 -> 0 | D10: =($R10*Deliveries!D10)/1000000 -> 0 | E10: =($R10*Deliveries!E10)/1000000 -> 0 | F10: =($R10*Deliveries!F10)/1000000 -> 0 | G10: =($R10*Deliveries!G10)/1000000 -> 0 | H10: =($R10*Deliveries!H10)*H19/1000000 -> 0 | I10: =($R10*Deliveries!I10)*I19/1000000 -> 43.75 | J10: =($R10*Deliveries!J10)*J19/1000000 -> 3622.3958 | K10: =($R10*Deliveries!K10)*K19/1000000 -> 7460.6895 | L10: =($R10*Deliveries!L10)*L19/1000000 -> 11937.103 | M10: =($R10*Deliveries!M10)*M19/1000000 -> 13130.813 | N10: =($R10*Deliveries!N10)*N19/1000000 -> 14443.895 | O10: =($R10*Deliveries!O10)*O19/1000000 -> 15599.406 | ... Q10: =($R10*Deliveries!Q10)*Q19/1000000 -> 17521.253 | R10: =AVERAGE('Average Prices'!C18:D18) -> 175000
B11: Total | C11: =SUM(C5:C10) -> 3740.973 | D11: =SUM(D5:D10) -> 6350.766 | E11: =SUM(E5:E10) -> 9641.3 | F11: ='P&L Input'!F4/1000 -> 18514.983 | G11: ='P&L Input'!G4/1000 -> 20821 | H11: =SUM(H5:H10) -> 33219.17 | I11: =SUM(I5:I10) -> 44967.683 | J11: =SUM(J5:J10) -> 62453.777 | K11: =SUM(K5:K10) -> 81523.291 | L11: =SUM(L5:L10) -> 93584.048 | M11: =SUM(M5:M10) -> 100240.63 | N11: =SUM(N5:N10) -> 106744.3 | O11: =SUM(O5:O10) -> 113335.65 | ... Q11: =SUM(Q5:Q10) -> 123467.68
B13: Selected case
B14: Tesla Model 3 | H14: =CHOOSE(Drivers!$C$3,'Revenue automotive'!H22,'Revenue automotive'!H30,'Revenue automotive'!H38) -> 1 | I14: =CHOOSE(Drivers!$C$3,'Revenue automotive'!I22,'Revenue automotive'!I30,'Revenue automotive'!I38) -> 1 | J14: =CHOOSE(Drivers!$C$3,'Revenue automotive'!J22,'Revenue automotive'!J30,'Revenue automotive'!J38) -> 1 | K14: =CHOOSE(Drivers!$C$3,'Revenue automotive'!K22,'Revenue automotive'!K30,'Revenue automotive'!K38) -> 1 | L14: =CHOOSE(Drivers!$C$3,'Revenue automotive'!L22,'Revenue automotive'!L30,'Revenue automotive'!L38) -> 1 | M14: =CHOOSE(Drivers!$C$3,'Revenue automotive'!M22,'Revenue automotive'!M30,'Revenue automotive'!M38) -> 1 | N14: =CHOOSE(Drivers!$C$3,'Revenue automotive'!N22,'Revenue automotive'!N30,'Revenue automotive'!N38) -> 1 | O14: =CHOOSE(Drivers!$C$3,'Revenue automotive'!O22,'Revenue automotive'!O30,'Revenue automotive'!O38) -> 1 | ... Q14: =CHOOSE(Drivers!$C$3,'Revenue automotive'!Q22,'Revenue automotive'!Q30,'Revenue automotive'!Q38) -> 1
B15: Tesla Model S and X | H15: =CHOOSE(Drivers!$C$3,'Revenue automotive'!H23,'Revenue automotive'!H31,'Revenue automotive'!H39) -> 1 | I15: =CHOOSE(Drivers!$C$3,'Revenue automotive'!I23,'Revenue automotive'!I31,'Revenue automotive'!I39) -> 1 | J15: =CHOOSE(Drivers!$C$3,'Revenue automotive'!J23,'Revenue automotive'!J31,'Revenue automotive'!J39) -> 1 | K15: =CHOOSE(Drivers!$C$3,'Revenue automotive'!K23,'Revenue automotive'!K31,'Revenue automotive'!K39) -> 1 | L15: =CHOOSE(Drivers!$C$3,'Revenue automotive'!L23,'Revenue automotive'!L31,'Revenue automotive'!L39) -> 1 | M15: =CHOOSE(Drivers!$C$3,'Revenue automotive'!M23,'Revenue automotive'!M31,'Revenue automotive'!M39) -> 1 | N15: =CHOOSE(Drivers!$C$3,'Revenue automotive'!N23,'Revenue automotive'!N31,'Revenue automotive'!N39) -> 1 | O15: =CHOOSE(Drivers!$C$3,'Revenue automotive'!O23,'Revenue automotive'!O31,'Revenue automotive'!O39) -> 1 | ... Q15: =CHOOSE(Drivers!$C$3,'Revenue automotive'!Q23,'Revenue automotive'!Q31,'Revenue automotive'!Q39) -> 1
B16: Tesla Model Y | H16: =CHOOSE(Drivers!$C$3,'Revenue automotive'!H24,'Revenue automotive'!H32,'Revenue automotive'!H40) -> 1 | I16: =CHOOSE(Drivers!$C$3,'Revenue automotive'!I24,'Revenue automotive'!I32,'Revenue automotive'!I40) -> 1 | J16: =CHOOSE(Drivers!$C$3,'Revenue automotive'!J24,'Revenue automotive'!J32,'Revenue automotive'!J40) -> 1 | K16: =CHOOSE(Drivers!$C$3,'Revenue automotive'!K24,'Revenue automotive'!K32,'Revenue automotive'!K40) -> 1 | L16: =CHOOSE(Drivers!$C$3,'Revenue automotive'!L24,'Revenue automotive'!L32,'Revenue automotive'!L40) -> 1 | M16: =CHOOSE(Drivers!$C$3,'Revenue automotive'!M24,'Revenue automotive'!M32,'Revenue automotive'!M40) -> 1 | N16: =CHOOSE(Drivers!$C$3,'Revenue automotive'!N24,'Revenue automotive'!N32,'Revenue automotive'!N40) -> 1 | O16: =CHOOSE(Drivers!$C$3,'Revenue automotive'!O24,'Revenue automotive'!O32,'Revenue automotive'!O40) -> 1 | ... Q16: =CHOOSE(Drivers!$C$3,'Revenue automotive'!Q24,'Revenue automotive'!Q32,'Revenue automotive'!Q40) -> 1
B17: Tesla Roadster 2 | H17: =CHOOSE(Drivers!$C$3,'Revenue automotive'!H25,'Revenue automotive'!H33,'Revenue automotive'!H41) -> 1 | I17: =CHOOSE(Drivers!$C$3,'Revenue automotive'!I25,'Revenue automotive'!I33,'Revenue automotive'!I41) -> 1 | J17: =CHOOSE(Drivers!$C$3,'Revenue automotive'!J25,'Revenue automotive'!J33,'Revenue automotive'!J41) -> 1 | K17: =CHOOSE(Drivers!$C$3,'Revenue automotive'!K25,'Revenue automotive'!K33,'Revenue automotive'!K41) -> 1 | L17: =CHOOSE(Drivers!$C$3,'Revenue automotive'!L25,'Revenue automotive'!L33,'Revenue automotive'!L41) -> 1 | M17: =CHOOSE(Drivers!$C$3,'Revenue automotive'!M25,'Revenue automotive'!M33,'Revenue automotive'!M41) -> 1 | N17: =CHOOSE(Drivers!$C$3,'Revenue automotive'!N25,'Revenue automotive'!N33,'Revenue automotive'!N41) -> 1 | O17: =CHOOSE(Drivers!$C$3,'Revenue automotive'!O25,'Revenue automotive'!O33,'Revenue automotive'!O41) -> 1 | ... Q17: =CHOOSE(Drivers!$C$3,'Revenue automotive'!Q25,'Revenue automotive'!Q33,'Revenue automotive'!Q41) -> 1
B18: Tesla Pickup | H18: =CHOOSE(Drivers!$C$3,'Revenue automotive'!H26,'Revenue automotive'!H34,'Revenue automotive'!H42) -> 1 | I18: =CHOOSE(Drivers!$C$3,'Revenue automotive'!I26,'Revenue automotive'!I34,'Revenue automotive'!I42) -> 1 | J18: =CHOOSE(Drivers!$C$3,'Revenue automotive'!J26,'Revenue automotive'!J34,'Revenue automotive'!J42) -> 1 | K18: =CHOOSE(Drivers!$C$3,'Revenue automotive'!K26,'Revenue automotive'!K34,'Revenue automotive'!K42) -> 1 | L18: =CHOOSE(Drivers!$C$3,'Revenue automotive'!L26,'Revenue automotive'!L34,'Revenue automotive'!L42) -> 1 | M18: =CHOOSE(Drivers!$C$3,'Revenue automotive'!M26,'Revenue automotive'!M34,'Revenue automotive'!M42) -> 1 | N18: =CHOOSE(Drivers!$C$3,'Revenue automotive'!N26,'Revenue automotive'!N34,'Revenue automotive'!N42) -> 1 | O18: =CHOOSE(Drivers!$C$3,'Revenue automotive'!O26,'Revenue automotive'!O34,'Revenue automotive'!O42) -> 1 | ... Q18: =CHOOSE(Drivers!$C$3,'Revenue automotive'!Q26,'Revenue automotive'!Q34,'Revenue automotive'!Q42) -> 1
B19: Tesla Semi | H19: =CHOOSE(Drivers!$C$3,'Revenue automotive'!H27,'Revenue automotive'!H35,'Revenue automotive'!H43) -> 1 | I19: =CHOOSE(Drivers!$C$3,'Revenue automotive'!I27,'Revenue automotive'!I35,'Revenue automotive'!I43) -> 1 | J19: =CHOOSE(Drivers!$C$3,'Revenue automotive'!J27,'Revenue automotive'!J35,'Revenue automotive'!J43) -> 1 | K19: =CHOOSE(Drivers!$C$3,'Revenue automotive'!K27,'Revenue automotive'!K35,'Revenue automotive'!K43) -> 1 | L19: =CHOOSE(Drivers!$C$3,'Revenue automotive'!L27,'Revenue automotive'!L35,'Revenue automotive'!L43) -> 1 | M19: =CHOOSE(Drivers!$C$3,'Revenue automotive'!M27,'Revenue automotive'!M35,'Revenue automotive'!M43) -> 1 | N19: =CHOOSE(Drivers!$C$3,'Revenue automotive'!N27,'Revenue automotive'!N35,'Revenue automotive'!N43) -> 1 | O19: =CHOOSE(Drivers!$C$3,'Revenue automotive'!O27,'Revenue automotive'!O35,'Revenue automotive'!O43) -> 1 | ... Q19: =CHOOSE(Drivers!$C$3,'Revenue automotive'!Q27,'Revenue automotive'!Q35,'Revenue automotive'!Q43) -> 1
B21: Best case
B22: Tesla Model 3 | H22: 1.02 | I22: 1.02 | J22: 1.02 | K22: 1.02 | L22: 1.02 | M22: 1.02 | N22: 1.02 | O22: 1.02 | P22: 1.02 | Q22: 1.02
B23: Tesla Model S and X | H23: 1.02 | I23: 1.02 | J23: 1.02 | K23: 1.02 | L23: 1.02 | M23: 1.02 | N23: 1.02 | O23: 1.02 | P23: 1.02 | Q23: 1.02
B24: Tesla Model Y | H24: 1.02 | I24: 1.02 | J24: 1.02 | K24: 1.02 | L24: 1.02 | M24: 1.02 | N24: 1.02 | O24: 1.02 | P24: 1.02 | Q24: 1.02
B25: Tesla Roadster 2 | H25: 1.02 | I25: 1.02 | J25: 1.02 | K25: 1.02 | L25: 1.02 | M25: 1.02 | N25: 1.02 | O25: 1.02 | P25: 1.02 | Q25: 1.02
B26: Tesla Pickup | H26: 1.02 | I26: 1.02 | J26: 1.02 | K26: 1.02 | L26: 1.02 | M26: 1.02 | N26: 1.02 | O26: 1.02 | P26: 1.02 | Q26: 1.02
B27: Tesla Semi | H27: 1.02 | I27: 1.02 | J27: 1.02 | K27: 1.02 | L27: 1.02 | M27: 1.02 | N27: 1.02 | O27: 1.02 | P27: 1.02 | Q27: 1.02
B29: Base case
B30: Tesla Model 3 | H30: 1 | I30: 1 | J30: 1 | K30: 1 | L30: 1 | M30: 1 | N30: 1 | O30: 1 | P30: 1 | Q30: 1
B31: Tesla Model S and X | H31: 1 | I31: 1 | J31: 1 | K31: 1 | L31: 1 | M31: 1 | N31: 1 | O31: 1 | P31: 1 | Q31: 1
B32: Tesla Model Y | H32: 1 | I32: 1 | J32: 1 | K32: 1 | L32: 1 | M32: 1 | N32: 1 | O32: 1 | P32: 1 | Q32: 1
B33: Tesla Roadster 2 | H33: 1 | I33: 1 | J33: 1 | K33: 1 | L33: 1 | M33: 1 | N33: 1 | O33: 1 | P33: 1 | Q33: 1
B34: Tesla Pickup | H34: 1 | I34: 1 | J34: 1 | K34: 1 | L34: 1 | M34: 1 | N34: 1 | O34: 1 | P34: 1 | Q34: 1
B35: Tesla Semi | H35: 1 | I35: 1 | J35: 1 | K35: 1 | L35: 1 | M35: 1 | N35: 1 | O35: 1 | P35: 1 | Q35: 1
B37: Worst case
B38: Tesla Model 3 | H38: 0.98 | I38: 0.98 | J38: 0.98 | K38: 0.98 | L38: 0.98 | M38: 0.98 | N38: 0.98 | O38: 0.98 | P38: 0.98 | Q38: 0.98
B39: Tesla Model S and X | H39: 0.98 | I39: 0.98 | J39: 0.98 | K39: 0.98 | L39: 0.98 | M39: 0.98 | N39: 0.98 | O39: 0.98 | P39: 0.98 | Q39: 0.98
B40: Tesla Model Y | H40: 0.98 | I40: 0.98 | J40: 0.98 | K40: 0.98 | L40: 0.98 | M40: 0.98 | N40: 0.98 | O40: 0.98 | P40: 0.98 | Q40: 0.98
B41: Tesla Roadster 2 | H41: 0.98 | I41: 0.98 | J41: 0.98 | K41: 0.98 | L41: 0.98 | M41: 0.98 | N41: 0.98 | O41: 0.98 | P41: 0.98 | Q41: 0.98
B42: Tesla Pickup | H42: 0.98 | I42: 0.98 | J42: 0.98 | K42: 0.98 | L42: 0.98 | M42: 0.98 | N42: 0.98 | O42: 0.98 | P42: 0.98 | Q42: 0.98
B43: Tesla Semi | H43: 0.98 | I43: 0.98 | J43: 0.98 | K43: 0.98 | L43: 0.98 | M43: 0.98 | N43: 0.98 | O43: 0.98 | P43: 0.98 | Q43: 0.98

Sheet GP% automotive
B1: GP %
B3: Comparables 2019
B5: Vehicle | C5: Comparable companies | D5: GP % Comp. 1 | E5: GP % Comp. 2 | F5: GP % Comp. 3 | H5: Average
B6: Tesla Model 3 | C6: GM, Ford, Fiat Chrysler | D6: 0.187 | E6: =(((155900-134693)/155900)+((160338-136269)/160338))/2 -> 0.14307182 | F6: =(((108187-93164)/108187)+((110412-95011)/110412))/2 -> 0.13917403 | H6: =C16 -> 0.22344388 | I6: Historic
B7: Tesla Model S and X | C7: BMW, Mercedes Cars, Volkswagen | D7: =((13620/91682)+(13928/85846))/2 -> 0.15540049 | E7: =((33067/167362)+(29165/172745))/2 -> 0.18320519 | F7: 0.172 | H7: =C17 -> 0.22344388 | I7: Historic
B8: Tesla Model Y | C8: GM, Ford, Fiat Chrysler | D8: 0.187 | E8: =(((155900-134693)/155900)+((160338-136269)/160338))/2 -> 0.14307182 | F8: =(((108187-93164)/108187)+((110412-95011)/110412))/2 -> 0.13917403 | H8: =AVERAGE(D8:F8) -> 0.15641528 | I8: Comparables
B9: Tesla Roadster 2 | C9: Jaguar, Porsche, Ferrari | D9: =(((24214-15670)/24214)+((25786-16328)/25786))/2 -> 0.35982095 | E9: 0.44 | F9: =(((3766-1805)/3766)+((3420-1623)/3420))/2 -> 0.52307511 | H9: =AVERAGE(D9:F9) -> 0.44096535 | I9: Comparables
B10: Tesla Pickup | C10: GM, Ford, Fiat Chrysler | D10: =D6 -> 0.187 | E10: =E6 -> 0.14307182 | F10: =F6 -> 0.13917403 | H10: =AVERAGE(D10:F10) -> 0.15641528 | I10: Comparables
B11: Tesla Semi | C11: Scania, MAN, Paccar | D11: 0.23 | E11: 0.23 | F11: =(((24120-20556)/24120)+((22139-18925)/22139))/2 -> 0.14646743 | H11: =AVERAGE(D11:F11) -> 0.20215581 | I11: Comparables
B13: Historical
B15: Vehicle | C15: Historic Average GP%
B16: Tesla Model 3 | C16: =AVERAGE('P&L Input'!F29:G29) -> 0.22344388
B17: Tesla Model S and X | C17: =AVERAGE('P&L Input'!F29:G29) -> 0.22344388
B18: Tesla Model Y | C18: n.a.
B19: Tesla Roadster 2 | C19: n.a.
B20: Tesla Pickup | C20: n.a.
B21: Tesla Semi | C21: n.a.

Sheet GP automotive
B1: Gross Profit
C3: Tesla Gross Profit (in mln $)
B4: Vehicle | C4: 2015 Act | D4: 2016 Act | E4: 2017 Act | F4: 2018 Act | G4: 2019 Act | H4: 2020 Fcst | I4: 2021 Fcst | J4: 2022 Fcst | K4: 2023 Fcst | L4: 2024 Fcst | M4: 2025 Fcst | N4: 2026 Fcst | O4: 2027 Fcst | P4: 2028 Fcst | Q4: 2029 Fcst
B5: Tesla Model 3 | C5: n.a. | D5: n.a. | E5: n.a. | F5: n.a. | G5: n.a. | H5: =H14*'Revenue automotive'!H5 -> 5824.2481 | I5: =I14*'Revenue automotive'!I5 -> 6406.6729 | J5: =J14*'Revenue automotive'!J5 -> 7047.3402 | K5: =K14*'Revenue automotive'!K5 -> 7611.1274 | L5: =L14*'Revenue automotive'!L5 -> 8220.0176 | M5: =M14*'Revenue automotive'!M5 -> 8548.8183 | N5: =N14*'Revenue automotive'!N5 -> 8890.771 | O5: =O14*'Revenue automotive'!O5 -> 9246.4019 | ... Q5: =Q14*'Revenue automotive'!Q5 -> 10000.908
B6: Tesla Model S and X | C6: n.a. | D6: n.a. | E6: n.a. | F6: n.a. | G6: n.a. | H6: =H15*'Revenue automotive'!H6 -> 1574.3287 | I6: =I15*'Revenue automotive'!I6 -> 1637.3019 | J6: =J15*'Revenue automotive'!J6 -> 1702.7939 | K6: =K15*'Revenue automotive'!K6 -> 1770.9057 | L6: =L15*'Revenue automotive'!L6 -> 1841.7419 | M6: =M15*'Revenue automotive'!M6 -> 1915.4116 | N6: =N15*'Revenue automotive'!N6 -> 1992.0281 | O6: =O15*'Revenue automotive'!O6 -> 2071.7092 | ... Q6: =Q15*'Revenue automotive'!Q6 -> 2240.7607
B7: Tesla Model Y | C7: 0 | D7: 0 | E7: 0 | F7: 0 | G7: =G16*'Revenue automotive'!G7 -> 0 | H7: =H16*'Revenue automotive'!H7 -> 16.83091 | I7: =I16*'Revenue automotive'!I7 -> 1393.5593 | J7: =J16*'Revenue automotive'!J7 -> 2870.1759 | K7: =K16*'Revenue automotive'!K7 -> 4592.2814 | L7: =L16*'Revenue automotive'!L7 -> 5051.5096 | M7: =M16*'Revenue automotive'!M7 -> 5556.6605 | N7: =N16*'Revenue automotive'!N7 -> 6001.1934 | ... Q7: =Q16*'Revenue automotive'!Q7 -> 7010.162
B8: Tesla Roadster 2 | C8: 0 | D8: 0 | E8: 0 | F8: 0 | G8: =G17*'Revenue automotive'!G8 -> 0 | H8: =H17*'Revenue automotive'!H8 -> 0 | I8: =I17*'Revenue automotive'!I8 -> 0 | J8: =J17*'Revenue automotive'!J8 -> 49.608602 | K8: =K17*'Revenue automotive'!K8 -> 99.217205 | L8: =L17*'Revenue automotive'!L8 -> 148.82581 | M8: =M17*'Revenue automotive'!M8 -> 163.70839 | N8: =N17*'Revenue automotive'!N8 -> 180.07923 | ... Q8: =Q17*'Revenue automotive'!Q8 -> 218.44619
B9: Tesla Pickup | C9: 0 | D9: 0 | E9: 0 | F9: 0 | G9: =G18*'Revenue automotive'!G9 -> 0 | H9: =H18*'Revenue automotive'!H9 -> 0 | I9: =I18*'Revenue automotive'!I9 -> 2.2836632 | J9: =J18*'Revenue automotive'!J9 -> 189.08187 | K9: =K18*'Revenue automotive'!K9 -> 389.43318 | L9: =L18*'Revenue automotive'!L9 -> 623.09309 | M9: =M18*'Revenue automotive'!M9 -> 685.4024 | N9: =N18*'Revenue automotive'!N9 -> 753.94264 | ... Q9: =Q18*'Revenue automotive'!Q9 -> 914.57464
B10: Tesla Semi | C10: 0 | D10: 0 | E10: 0 | F10: 0 | G10: =G19*'Revenue automotive'!G10 -> 0 | H10: =H19*'Revenue automotive'!H10 -> 0 | I10: =I19*'Revenue automotive'!I10 -> 8.8443168 | J10: =J19*'Revenue automotive'!J10 -> 732.28837 | K10: =K19*'Revenue automotive'!K10 -> 1508.2217 | L10: =L19*'Revenue automotive'!L10 -> 2413.1548 | M10: =M19*'Revenue automotive'!M10 -> 2654.4703 | N10: =N19*'Revenue automotive'!N10 -> 2919.9173 | ... Q10: =Q19*'Revenue automotive'!Q10 -> 3542.0232
B11: Total | C11: =('P&L Input'!C4+'P&L Input'!C8)/1000 -> 917.671 | D11: =('P&L Input'!D4+'P&L Input'!D8)/1000 -> 1600.685 | E11: =('P&L Input'!E4+'P&L Input'!E8)/1000 -> 2208.596 | F11: =('P&L Input'!F4+'P&L Input'!F8)/1000 -> 4340.986 | G11: =('P&L Input'!G4+'P&L Input'!G8)/1000 -> 4423 | H11: =SUM(H5:H10) -> 7415.4077 | I11: =SUM(I5:I10) -> 9448.662 | J11: =SUM(J5:J10) -> 12591.289 | K11: =SUM(K5:K10) -> 15971.187 | L11: =SUM(L5:L10) -> 18298.343 | M11: =SUM(M5:M10) -> 19524.471 | N11: =SUM(N5:N10) -> 20737.932 | O11: =SUM(O5:O10) -> 21961.654 | ... Q11: =SUM(Q5:Q10) -> 23926.875
B13: Selected case
B14: Tesla Model 3 | G14: =CHOOSE(Drivers!$C$3,'GP automotive'!G22,'GP automotive'!G30,'GP automotive'!G38) -> 0.22344388 | H14: =CHOOSE(Drivers!$C$3,'GP automotive'!H22,'GP automotive'!H30,'GP automotive'!H38) -> 0.22344388 | I14: =CHOOSE(Drivers!$C$3,'GP automotive'!I22,'GP automotive'!I30,'GP automotive'!I38) -> 0.22344388 | J14: =CHOOSE(Drivers!$C$3,'GP automotive'!J22,'GP automotive'!J30,'GP automotive'!J38) -> 0.22344388 | K14: =CHOOSE(Drivers!$C$3,'GP automotive'!K22,'GP automotive'!K30,'GP automotive'!K38) -> 0.22344388 | L14: =CHOOSE(Drivers!$C$3,'GP automotive'!L22,'GP automotive'!L30,'GP automotive'!L38) -> 0.22344388 | M14: =CHOOSE(Drivers!$C$3,'GP automotive'!M22,'GP automotive'!M30,'GP automotive'!M38) -> 0.22344388 | N14: =CHOOSE(Drivers!$C$3,'GP automotive'!N22,'GP automotive'!N30,'GP automotive'!N38) -> 0.22344388 | ... Q14: =CHOOSE(Drivers!$C$3,'GP automotive'!Q22,'GP automotive'!Q30,'GP automotive'!Q38) -> 0.22344388
B15: Tesla Model S and X | G15: =CHOOSE(Drivers!$C$3,'GP automotive'!G23,'GP automotive'!G31,'GP automotive'!G39) -> 0.22344388 | H15: =CHOOSE(Drivers!$C$3,'GP automotive'!H23,'GP automotive'!H31,'GP automotive'!H39) -> 0.22344388 | I15: =CHOOSE(Drivers!$C$3,'GP automotive'!I23,'GP automotive'!I31,'GP automotive'!I39) -> 0.22344388 | J15: =CHOOSE(Drivers!$C$3,'GP automotive'!J23,'GP automotive'!J31,'GP automotive'!J39) -> 0.22344388 | K15: =CHOOSE(Drivers!$C$3,'GP automotive'!K23,'GP automotive'!K31,'GP automotive'!K39) -> 0.22344388 | L15: =CHOOSE(Drivers!$C$3,'GP automotive'!L23,'GP automotive'!L31,'GP automotive'!L39) -> 0.22344388 | M15: =CHOOSE(Drivers!$C$3,'GP automotive'!M23,'GP automotive'!M31,'GP automotive'!M39) -> 0.22344388 | N15: =CHOOSE(Drivers!$C$3,'GP automotive'!N23,'GP automotive'!N31,'GP automotive'!N39) -> 0.22344388 | ... Q15: =CHOOSE(Drivers!$C$3,'GP automotive'!Q23,'GP automotive'!Q31,'GP automotive'!Q39) -> 0.22344388
B16: Tesla Model Y | G16: =CHOOSE(Drivers!$C$3,'GP automotive'!G24,'GP automotive'!G32,'GP automotive'!G40) -> 0.15641528 | H16: =CHOOSE(Drivers!$C$3,'GP automotive'!H24,'GP automotive'!H32,'GP automotive'!H40) -> 0.15641528 | I16: =CHOOSE(Drivers!$C$3,'GP automotive'!I24,'GP automotive'!I32,'GP automotive'!I40) -> 0.15641528 | J16: =CHOOSE(Drivers!$C$3,'GP automotive'!J24,'GP automotive'!J32,'GP automotive'!J40) -> 0.15641528 | K16: =CHOOSE(Drivers!$C$3,'GP automotive'!K24,'GP automotive'!K32,'GP automotive'!K40) -> 0.15641528 | L16: =CHOOSE(Drivers!$C$3,'GP automotive'!L24,'GP automotive'!L32,'GP automotive'!L40) -> 0.15641528 | M16: =CHOOSE(Drivers!$C$3,'GP automotive'!M24,'GP automotive'!M32,'GP automotive'!M40) -> 0.15641528 | N16: =CHOOSE(Drivers!$C$3,'GP automotive'!N24,'GP automotive'!N32,'GP automotive'!N40) -> 0.15641528 | ... Q16: =CHOOSE(Drivers!$C$3,'GP automotive'!Q24,'GP automotive'!Q32,'GP automotive'!Q40) -> 0.15641528
B17: Tesla Roadster 2 | G17: =CHOOSE(Drivers!$C$3,'GP automotive'!G25,'GP automotive'!G33,'GP automotive'!G41) -> 0.44096535 | H17: =CHOOSE(Drivers!$C$3,'GP automotive'!H25,'GP automotive'!H33,'GP automotive'!H41) -> 0.44096535 | I17: =CHOOSE(Drivers!$C$3,'GP automotive'!I25,'GP automotive'!I33,'GP automotive'!I41) -> 0.44096535 | J17: =CHOOSE(Drivers!$C$3,'GP automotive'!J25,'GP automotive'!J33,'GP automotive'!J41) -> 0.44096535 | K17: =CHOOSE(Drivers!$C$3,'GP automotive'!K25,'GP automotive'!K33,'GP automotive'!K41) -> 0.44096535 | L17: =CHOOSE(Drivers!$C$3,'GP automotive'!L25,'GP automotive'!L33,'GP automotive'!L41) -> 0.44096535 | M17: =CHOOSE(Drivers!$C$3,'GP automotive'!M25,'GP automotive'!M33,'GP automotive'!M41) -> 0.44096535 | N17: =CHOOSE(Drivers!$C$3,'GP automotive'!N25,'GP automotive'!N33,'GP automotive'!N41) -> 0.44096535 | ... Q17: =CHOOSE(Drivers!$C$3,'GP automotive'!Q25,'GP automotive'!Q33,'GP automotive'!Q41) -> 0.44096535
B18: Tesla Pickup | G18: =CHOOSE(Drivers!$C$3,'GP automotive'!G26,'GP automotive'!G34,'GP automotive'!G42) -> 0.15641528 | H18: =CHOOSE(Drivers!$C$3,'GP automotive'!H26,'GP automotive'!H34,'GP automotive'!H42) -> 0.15641528 | I18: =CHOOSE(Drivers!$C$3,'GP automotive'!I26,'GP automotive'!I34,'GP automotive'!I42) -> 0.15641528 | J18: =CHOOSE(Drivers!$C$3,'GP automotive'!J26,'GP automotive'!J34,'GP automotive'!J42) -> 0.15641528 | K18: =CHOOSE(Drivers!$C$3,'GP automotive'!K26,'GP automotive'!K34,'GP automotive'!K42) -> 0.15641528 | L18: =CHOOSE(Drivers!$C$3,'GP automotive'!L26,'GP automotive'!L34,'GP automotive'!L42) -> 0.15641528 | M18: =CHOOSE(Drivers!$C$3,'GP automotive'!M26,'GP automotive'!M34,'GP automotive'!M42) -> 0.15641528 | N18: =CHOOSE(Drivers!$C$3,'GP automotive'!N26,'GP automotive'!N34,'GP automotive'!N42) -> 0.15641528 | ... Q18: =CHOOSE(Drivers!$C$3,'GP automotive'!Q26,'GP automotive'!Q34,'GP automotive'!Q42) -> 0.15641528
B19: Tesla Semi | G19: =CHOOSE(Drivers!$C$3,'GP automotive'!G27,'GP automotive'!G35,'GP automotive'!G43) -> 0.20215581 | H19: =CHOOSE(Drivers!$C$3,'GP automotive'!H27,'GP automotive'!H35,'GP automotive'!H43) -> 0.20215581 | I19: =CHOOSE(Drivers!$C$3,'GP automotive'!I27,'GP automotive'!I35,'GP automotive'!I43) -> 0.20215581 | J19: =CHOOSE(Drivers!$C$3,'GP automotive'!J27,'GP automotive'!J35,'GP automotive'!J43) -> 0.20215581 | K19: =CHOOSE(Drivers!$C$3,'GP automotive'!K27,'GP automotive'!K35,'GP automotive'!K43) -> 0.20215581 | L19: =CHOOSE(Drivers!$C$3,'GP automotive'!L27,'GP automotive'!L35,'GP automotive'!L43) -> 0.20215581 | M19: =CHOOSE(Drivers!$C$3,'GP automotive'!M27,'GP automotive'!M35,'GP automotive'!M43) -> 0.20215581 | N19: =CHOOSE(Drivers!$C$3,'GP automotive'!N27,'GP automotive'!N35,'GP automotive'!N43) -> 0.20215581 | ... Q19: =CHOOSE(Drivers!$C$3,'GP automotive'!Q27,'GP automotive'!Q35,'GP automotive'!Q43) -> 0.20215581
B21: Best case
B22: Tesla Model 3 | G22: =G30+1.5% -> 0.23844388 | H22: =H30+1.5% -> 0.23844388 | I22: =I30+1.5% -> 0.23844388 | J22: =J30+1.5% -> 0.23844388 | K22: =K30+1.5% -> 0.23844388 | L22: =L30+1.5% -> 0.23844388 | M22: =M30+1.5% -> 0.23844388 | N22: =N30+1.5% -> 0.23844388 | ... Q22: =Q30+1.5% -> 0.23844388
B23: Tesla Model S and X | G23: =G31+1.5% -> 0.23844388 | H23: =H31+1.5% -> 0.23844388 | I23: =I31+1.5% -> 0.23844388 | J23: =J31+1.5% -> 0.23844388 | K23: =K31+1.5% -> 0.23844388 | L23: =L31+1.5% -> 0.23844388 | M23: =M31+1.5% -> 0.23844388 | N23: =N31+1.5% -> 0.23844388 | ... Q23: =Q31+1.5% -> 0.23844388
B24: Tesla Model Y | G24: =G32+1.5% -> 0.17141528 | H24: =H32+1.5% -> 0.17141528 | I24: =I32+1.5% -> 0.17141528 | J24: =J32+1.5% -> 0.17141528 | K24: =K32+1.5% -> 0.17141528 | L24: =L32+1.5% -> 0.17141528 | M24: =M32+1.5% -> 0.17141528 | N24: =N32+1.5% -> 0.17141528 | ... Q24: =Q32+1.5% -> 0.17141528
B25: Tesla Roadster 2 | G25: =G33+1.5% -> 0.45596535 | H25: =H33+1.5% -> 0.45596535 | I25: =I33+1.5% -> 0.45596535 | J25: =J33+1.5% -> 0.45596535 | K25: =K33+1.5% -> 0.45596535 | L25: =L33+1.5% -> 0.45596535 | M25: =M33+1.5% -> 0.45596535 | N25: =N33+1.5% -> 0.45596535 | ... Q25: =Q33+1.5% -> 0.45596535
B26: Tesla Pickup | G26: =G34+1.5% -> 0.17141528 | H26: =H34+1.5% -> 0.17141528 | I26: =I34+1.5% -> 0.17141528 | J26: =J34+1.5% -> 0.17141528 | K26: =K34+1.5% -> 0.17141528 | L26: =L34+1.5% -> 0.17141528 | M26: =M34+1.5% -> 0.17141528 | N26: =N34+1.5% -> 0.17141528 | ... Q26: =Q34+1.5% -> 0.17141528
B27: Tesla Semi | G27: =G35+1.5% -> 0.21715581 | H27: =H35+1.5% -> 0.21715581 | I27: =I35+1.5% -> 0.21715581 | J27: =J35+1.5% -> 0.21715581 | K27: =K35+1.5% -> 0.21715581 | L27: =L35+1.5% -> 0.21715581 | M27: =M35+1.5% -> 0.21715581 | N27: =N35+1.5% -> 0.21715581 | ... Q27: =Q35+1.5% -> 0.21715581
B29: Base case
B30: Tesla Model 3 | G30: ='GP% automotive'!$H6 -> 0.22344388 | H30: ='GP% automotive'!$H6 -> 0.22344388 | I30: ='GP% automotive'!$H6 -> 0.22344388 | J30: ='GP% automotive'!$H6 -> 0.22344388 | K30: ='GP% automotive'!$H6 -> 0.22344388 | L30: ='GP% automotive'!$H6 -> 0.22344388 | M30: ='GP% automotive'!$H6 -> 0.22344388 | N30: ='GP% automotive'!$H6 -> 0.22344388 | ... Q30: ='GP% automotive'!$H6 -> 0.22344388
B31: Tesla Model S and X | G31: ='GP% automotive'!$H7 -> 0.22344388 | H31: ='GP% automotive'!$H7 -> 0.22344388 | I31: ='GP% automotive'!$H7 -> 0.22344388 | J31: ='GP% automotive'!$H7 -> 0.22344388 | K31: ='GP% automotive'!$H7 -> 0.22344388 | L31: ='GP% automotive'!$H7 -> 0.22344388 | M31: ='GP% automotive'!$H7 -> 0.22344388 | N31: ='GP% automotive'!$H7 -> 0.22344388 | ... Q31: ='GP% automotive'!$H7 -> 0.22344388
B32: Tesla Model Y | G32: ='GP% automotive'!$H8 -> 0.15641528 | H32: ='GP% automotive'!$H8 -> 0.15641528 | I32: ='GP% automotive'!$H8 -> 0.15641528 | J32: ='GP% automotive'!$H8 -> 0.15641528 | K32: ='GP% automotive'!$H8 -> 0.15641528 | L32: ='GP% automotive'!$H8 -> 0.15641528 | M32: ='GP% automotive'!$H8 -> 0.15641528 | N32: ='GP% automotive'!$H8 -> 0.15641528 | ... Q32: ='GP% automotive'!$H8 -> 0.15641528
B33: Tesla Roadster 2 | G33: ='GP% automotive'!$H9 -> 0.44096535 | H33: ='GP% automotive'!$H9 -> 0.44096535 | I33: ='GP% automotive'!$H9 -> 0.44096535 | J33: ='GP% automotive'!$H9 -> 0.44096535 | K33: ='GP% automotive'!$H9 -> 0.44096535 | L33: ='GP% automotive'!$H9 -> 0.44096535 | M33: ='GP% automotive'!$H9 -> 0.44096535 | N33: ='GP% automotive'!$H9 -> 0.44096535 | ... Q33: ='GP% automotive'!$H9 -> 0.44096535
B34: Tesla Pickup | G34: ='GP% automotive'!$H10 -> 0.15641528 | H34: ='GP% automotive'!$H10 -> 0.15641528 | I34: ='GP% automotive'!$H10 -> 0.15641528 | J34: ='GP% automotive'!$H10 -> 0.15641528 | K34: ='GP% automotive'!$H10 -> 0.15641528 | L34: ='GP% automotive'!$H10 -> 0.15641528 | M34: ='GP% automotive'!$H10 -> 0.15641528 | N34: ='GP% automotive'!$H10 -> 0.15641528 | ... Q34: ='GP% automotive'!$H10 -> 0.15641528
B35: Tesla Semi | G35: ='GP% automotive'!$H11 -> 0.20215581 | H35: ='GP% automotive'!$H11 -> 0.20215581 | I35: ='GP% automotive'!$H11 -> 0.20215581 | J35: ='GP% automotive'!$H11 -> 0.20215581 | K35: ='GP% automotive'!$H11 -> 0.20215581 | L35: ='GP% automotive'!$H11 -> 0.20215581 | M35: ='GP% automotive'!$H11 -> 0.20215581 | N35: ='GP% automotive'!$H11 -> 0.20215581 | ... Q35: ='GP% automotive'!$H11 -> 0.20215581
B37: Worst case
B38: Tesla Model 3 | G38: =G30-1.5% -> 0.20844388 | H38: =H30-1.5% -> 0.20844388 | I38: =I30-1.5% -> 0.20844388 | J38: =J30-1.5% -> 0.20844388 | K38: =K30-1.5% -> 0.20844388 | L38: =L30-1.5% -> 0.20844388 | M38: =M30-1.5% -> 0.20844388 | N38: =N30-1.5% -> 0.20844388 | ... Q38: =Q30-1.5% -> 0.20844388
B39: Tesla Model S and X | G39: =G31-1.5% -> 0.20844388 | H39: =H31-1.5% -> 0.20844388 | I39: =I31-1.5% -> 0.20844388 | J39: =J31-1.5% -> 0.20844388 | K39: =K31-1.5% -> 0.20844388 | L39: =L31-1.5% -> 0.20844388 | M39: =M31-1.5% -> 0.20844388 | N39: =N31-1.5% -> 0.20844388 | ... Q39: =Q31-1.5% -> 0.20844388
B40: Tesla Model Y | G40: =G32-1.5% -> 0.14141528 | H40: =H32-1.5% -> 0.14141528 | I40: =I32-1.5% -> 0.14141528 | J40: =J32-1.5% -> 0.14141528 | K40: =K32-1.5% -> 0.14141528 | L40: =L32-1.5% -> 0.14141528 | M40: =M32-1.5% -> 0.14141528 | N40: =N32-1.5% -> 0.14141528 | ... Q40: =Q32-1.5% -> 0.14141528
B41: Tesla Roadster 2 | G41: =G33-1.5% -> 0.42596535 | H41: =H33-1.5% -> 0.42596535 | I41: =I33-1.5% -> 0.42596535 | J41: =J33-1.5% -> 0.42596535 | K41: =K33-1.5% -> 0.42596535 | L41: =L33-1.5% -> 0.42596535 | M41: =M33-1.5% -> 0.42596535 | N41: =N33-1.5% -> 0.42596535 | ... Q41: =Q33-1.5% -> 0.42596535
B42: Tesla Pickup | G42: =G34-1.5% -> 0.14141528 | H42: =H34-1.5% -> 0.14141528 | I42: =I34-1.5% -> 0.14141528 | J42: =J34-1.5% -> 0.14141528 | K42: =K34-1.5% -> 0.14141528 | L42: =L34-1.5% -> 0.14141528 | M42: =M34-1.5% -> 0.14141528 | N42: =N34-1.5% -> 0.14141528 | ... Q42: =Q34-1.5% -> 0.14141528
B43: Tesla Semi | G43: =G35-1.5% -> 0.18715581 | H43: =H35-1.5% -> 0.18715581 | I43: =I35-1.5% -> 0.18715581 | J43: =J35-1.5% -> 0.18715581 | K43: =K35-1.5% -> 0.18715581 | L43: =L35-1.5% -> 0.18715581 | M43: =M35-1.5% -> 0.18715581 | N43: =N35-1.5% -> 0.18715581 | ... Q43: =Q35-1.5% -> 0.18715581

Sheet Cost of sales automotive
B1: Cost of sales automotive
C3: Tesla Cost of sales (in mln $)
B4: Vehicle | C4: 2015 Act | D4: 2016 Act | E4: 2017 Act | F4: 2018 Act | G4: 2019 Act | H4: 2020 Fcst | I4: 2021 Fcst | J4: 2022 Fcst | K4: 2023 Fcst | L4: 2024 Fcst | M4: 2025 Fcst | N4: 2026 Fcst | O4: 2027 Fcst | P4: 2028 Fcst | Q4: 2029 Fcst
B5: Tesla Model 3 | C5: n.a. | D5: n.a. | E5: n.a. | F5: n.a. | G5: n.a. | H5: =-('Revenue automotive'!H5-'GP automotive'!H5) -> -20241.572 | I5: =-('Revenue automotive'!I5-'GP automotive'!I5) -> -22265.729 | J5: =-('Revenue automotive'!J5-'GP automotive'!J5) -> -24492.302 | K5: =-('Revenue automotive'!K5-'GP automotive'!K5) -> -26451.687 | L5: =-('Revenue automotive'!L5-'GP automotive'!L5) -> -28567.821 | M5: =-('Revenue automotive'!M5-'GP automotive'!M5) -> -29710.534 | N5: =-('Revenue automotive'!N5-'GP automotive'!N5) -> -30898.956 | O5: =-('Revenue automotive'!O5-'GP automotive'!O5) -> -32134.914 | ... Q5: =-('Revenue automotive'!Q5-'GP automotive'!Q5) -> -34757.123
B6: Tesla Model S and X | C6: n.a. | D6: n.a. | E6: n.a. | F6: n.a. | G6: n.a. | H6: =-('Revenue automotive'!H6-'GP automotive'!H6) -> -5471.4167 | I6: =-('Revenue automotive'!I6-'GP automotive'!I6) -> -5690.2734 | J6: =-('Revenue automotive'!J6-'GP automotive'!J6) -> -5917.8843 | K6: =-('Revenue automotive'!K6-'GP automotive'!K6) -> -6154.5997 | L6: =-('Revenue automotive'!L6-'GP automotive'!L6) -> -6400.7837 | M6: =-('Revenue automotive'!M6-'GP automotive'!M6) -> -6656.815 | N6: =-('Revenue automotive'!N6-'GP automotive'!N6) -> -6923.0876 | O6: =-('Revenue automotive'!O6-'GP automotive'!O6) -> -7200.0111 | ... Q6: =-('Revenue automotive'!Q6-'GP automotive'!Q6) -> -7787.532
B7: Tesla Model Y | C7: 0 | D7: 0 | E7: 0 | F7: 0 | G7: =-('Revenue automotive'!G7-'GP automotive'!G7) -> 0 | H7: =-('Revenue automotive'!H7-'GP automotive'!H7) -> -90.77309 | I7: =-('Revenue automotive'!I7-'GP automotive'!I7) -> -7515.7957 | J7: =-('Revenue automotive'!J7-'GP automotive'!J7) -> -15479.539 | K7: =-('Revenue automotive'!K7-'GP automotive'!K7) -> -24767.263 | L7: =-('Revenue automotive'!L7-'GP automotive'!L7) -> -27243.989 | M7: =-('Revenue automotive'!M7-'GP automotive'!M7) -> -29968.388 | N7: =-('Revenue automotive'!N7-'GP automotive'!N7) -> -32365.859 | ... Q7: =-('Revenue automotive'!Q7-'GP automotive'!Q7) -> -37807.466
B8: Tesla Roadster 2 | C8: 0 | D8: 0 | E8: 0 | F8: 0 | G8: =-('Revenue automotive'!G8-'GP automotive'!G8) -> 0 | H8: =-('Revenue automotive'!H8-'GP automotive'!H8) -> 0 | I8: =-('Revenue automotive'!I8-'GP automotive'!I8) -> 0 | J8: =-('Revenue automotive'!J8-'GP automotive'!J8) -> -62.891398 | K8: =-('Revenue automotive'!K8-'GP automotive'!K8) -> -125.7828 | L8: =-('Revenue automotive'!L8-'GP automotive'!L8) -> -188.67419 | M8: =-('Revenue automotive'!M8-'GP automotive'!M8) -> -207.54161 | N8: =-('Revenue automotive'!N8-'GP automotive'!N8) -> -228.29577 | ... Q8: =-('Revenue automotive'!Q8-'GP automotive'!Q8) -> -276.93556
B9: Tesla Pickup | C9: 0 | D9: 0 | E9: 0 | F9: 0 | G9: =-('Revenue automotive'!G9-'GP automotive'!G9) -> 0 | H9: =-('Revenue automotive'!H9-'GP automotive'!H9) -> 0 | I9: =-('Revenue automotive'!I9-'GP automotive'!I9) -> -12.316337 | J9: =-('Revenue automotive'!J9-'GP automotive'!J9) -> -1019.7634 | K9: =-('Revenue automotive'!K9-'GP automotive'!K9) -> -2100.3055 | L9: =-('Revenue automotive'!L9-'GP automotive'!L9) -> -3360.4888 | M9: =-('Revenue automotive'!M9-'GP automotive'!M9) -> -3696.5376 | N9: =-('Revenue automotive'!N9-'GP automotive'!N9) -> -4066.1914 | ... Q9: =-('Revenue automotive'!Q9-'GP automotive'!Q9) -> -4932.5179
B10: Tesla Semi | C10: 0 | D10: 0 | E10: 0 | F10: 0 | G10: =-('Revenue automotive'!G10-'GP automotive'!G10) -> 0 | H10: =-('Revenue automotive'!H10-'GP automotive'!H10) -> 0 | I10: =-('Revenue automotive'!I10-'GP automotive'!I10) -> -34.905683 | J10: =-('Revenue automotive'!J10-'GP automotive'!J10) -> -2890.1075 | K10: =-('Revenue automotive'!K10-'GP automotive'!K10) -> -5952.4677 | L10: =-('Revenue automotive'!L10-'GP automotive'!L10) -> -9523.9484 | M10: =-('Revenue automotive'!M10-'GP automotive'!M10) -> -10476.343 | N10: =-('Revenue automotive'!N10-'GP automotive'!N10) -> -11523.978 | ... Q10: =-('Revenue automotive'!Q10-'GP automotive'!Q10) -> -13979.23
B11: Total | C11: ='P&L Input'!C8/1000 -> -2823.302 | D11: ='P&L Input'!D8/1000 -> -4750.081 | E11: ='P&L Input'!E8/1000 -> -7432.704 | F11: ='P&L Input'!F8/1000 -> -14173.997 | G11: =-('Revenue automotive'!G11-'GP automotive'!G11) -> -16398 | H11: =SUM(H5:H10) -> -25803.762 | I11: =SUM(I5:I10) -> -35519.021 | J11: =SUM(J5:J10) -> -49862.488 | K11: =SUM(K5:K10) -> -65552.105 | L11: =SUM(L5:L10) -> -75285.705 | M11: =SUM(M5:M10) -> -80716.16 | N11: =SUM(N5:N10) -> -86006.367 | O11: =SUM(O5:O10) -> -91373.994 | ... Q11: =SUM(Q5:Q10) -> -99540.804

Sheet Revenue & GP autom
B1: Revenue and Gross Profit automotive
B3: Vehicle | C3: 2016 Act | D3: 2017 Act | E3: 2018 Act | F3: 2019 Act | G3: 2020 Fcst | H3: 2021 Fcst | I3: 2022 Fcst | J3: 2023 Fcst | K3: 2024 Fcst | L3: 2025 Fcst | M3: 2026 Fcst | N3: 2027 Fcst | O3: 2028 Fcst | P3: 2029 Fcst
B4: Revenue automotive | C4: ='Revenue automotive'!C11 -> 3740.973 | D4: ='Revenue automotive'!D11 -> 6350.766 | E4: ='Revenue automotive'!E11 -> 9641.3 | F4: ='Revenue automotive'!F11 -> 18514.983 | G4: ='Revenue automotive'!H11 -> 33219.17 | H4: ='Revenue automotive'!I11 -> 44967.683 | I4: ='Revenue automotive'!J11 -> 62453.777 | J4: ='Revenue automotive'!K11 -> 81523.291 | K4: ='Revenue automotive'!L11 -> 93584.048 | L4: ='Revenue automotive'!M11 -> 100240.63 | M4: ='Revenue automotive'!N11 -> 106744.3 | N4: ='Revenue automotive'!O11 -> 113335.65 | ... P4: ='Revenue automotive'!Q11 -> 123467.68
B5: Gross Profit automotive | C5: ='GP automotive'!C11 -> 917.671 | D5: ='GP automotive'!D11 -> 1600.685 | E5: ='GP automotive'!E11 -> 2208.596 | F5: ='GP automotive'!F11 -> 4340.986 | G5: ='GP automotive'!H11 -> 7415.4077 | H5: ='GP automotive'!I11 -> 9448.662 | I5: ='GP automotive'!J11 -> 12591.289 | J5: ='GP automotive'!K11 -> 15971.187 | K5: ='GP automotive'!L11 -> 18298.343 | L5: ='GP automotive'!M11 -> 19524.471 | M5: ='GP automotive'!N11 -> 20737.932 | N5: ='GP automotive'!O11 -> 21961.654 | ... P5: ='GP automotive'!Q11 -> 23926.875
B6: GP% | C6: =C5/C4 -> 0.24530276 | D6: =D5/D4 -> 0.25204597 | E6: =E5/E4 -> 0.22907658 | F6: =F5/F4 -> 0.23445801 | G6: =G5/G4 -> 0.22322676 | H6: =H5/H4 -> 0.21012117 | I6: =I5/I4 -> 0.20160973 | J6: =J5/J4 -> 0.19590949 | ... P6: =P5/P4 -> 0.19379059

Sheet Energy & Other
B14: Energy & Other

Sheet Revenue Energy & Other
B1: Revenue Energy & Other
C3: Tesla Revenue Energy & Other (in mln $)
B4: ($ in million) | C4: 2015 Act | D4: 2016 Act | E4: 2017 Act | F4: 2018 Act | G4: 2019 Act | H4: 2020 Fcst | I4: 2021 Fcst | J4: 2022 Fcst | K4: 2023 Fcst | L4: 2024 Fcst | M4: 2025 Fcst | N4: 2026 Fcst | O4: 2027 Fcst | P4: 2028 Fcst | Q4: 2029 Fcst
B5: Energy generation and storage | C5: ='P&L Input'!C5/1000 -> 14.477 | D5: ='P&L Input'!D5/1000 -> 181.394 | E5: ='P&L Input'!E5/1000 -> 1116.266 | F5: ='P&L Input'!F5/1000 -> 1555.244 | G5: ='P&L Input'!G5/1000 -> 1531 | H5: n.a. | I5: n.a. | J5: n.a. | K5: n.a. | L5: n.a. | M5: n.a. | N5: n.a. | O5: n.a. | P5: n.a. | Q5: n.a.
B6: Services and other | C6: ='P&L Input'!C6/1000 -> 290.575 | D6: ='P&L Input'!D6/1000 -> 467.972 | E6: ='P&L Input'!E6/1000 -> 1001.185 | F6: ='P&L Input'!F6/1000 -> 1391.041 | G6: ='P&L Input'!G6/1000 -> 2226 | H6: n.a. | I6: n.a. | J6: n.a. | K6: n.a. | L6: n.a. | M6: n.a. | N6: n.a. | O6: n.a. | P6: n.a. | Q6: n.a.
B7: Total Energy and Other | C7: =SUM(C5:C6) -> 305.052 | D7: =SUM(D5:D6) -> 649.366 | E7: =SUM(E5:E6) -> 2117.451 | F7: =SUM(F5:F6) -> 2946.285 | G7: =SUM(G5:G6) -> 3757 | H7: =G7*(1+H10) -> 4433.26 | I7: =H7*(1+I10) -> 4965.2512 | J7: =I7*(1+J10) -> 5362.4713 | K7: =J7*(1+K10) -> 5684.2196 | L7: =K7*(1+L10) -> 6025.2727 | M7: =L7*(1+M10) -> 6386.7891 | N7: =M7*(1+N10) -> 6769.9965 | O7: =N7*(1+O10) -> 7176.1962 | ... Q7: =P7*(1+Q10) -> 8063.1741
B9: Selected case
B10: Total Energy and Other | H10: =CHOOSE(Drivers!$C$3,'Revenue Energy & Other'!H14,'Revenue Energy & Other'!H17,'Revenue Energy & Other'!H20) -> 0.18 | I10: =CHOOSE(Drivers!$C$3,'Revenue Energy & Other'!I14,'Revenue Energy & Other'!I17,'Revenue Energy & Other'!I20) -> 0.12 | J10: =CHOOSE(Drivers!$C$3,'Revenue Energy & Other'!J14,'Revenue Energy & Other'!J17,'Revenue Energy & Other'!J20) -> 0.08 | K10: =CHOOSE(Drivers!$C$3,'Revenue Energy & Other'!K14,'Revenue Energy & Other'!K17,'Revenue Energy & Other'!K20) -> 0.06 | L10: =CHOOSE(Drivers!$C$3,'Revenue Energy & Other'!L14,'Revenue Energy & Other'!L17,'Revenue Energy & Other'!L20) -> 0.06 | M10: =CHOOSE(Drivers!$C$3,'Revenue Energy & Other'!M14,'Revenue Energy & Other'!M17,'Revenue Energy & Other'!M20) -> 0.06 | N10: =CHOOSE(Drivers!$C$3,'Revenue Energy & Other'!N14,'Revenue Energy & Other'!N17,'Revenue Energy & Other'!N20) -> 0.06 | O10: =CHOOSE(Drivers!$C$3,'Revenue Energy & Other'!O14,'Revenue Energy & Other'!O17,'Revenue Energy & Other'!O20) -> 0.06 | ... Q10: =CHOOSE(Drivers!$C$3,'Revenue Energy & Other'!Q14,'Revenue Energy & Other'!Q17,'Revenue Energy & Other'!Q20) -> 0.06
B12: Y-o-Y %
B13: Best case
B14: Total Energy and Other | H14: =H17+Drivers!$C$13 -> 0.2 | I14: =I17+Drivers!$C$13 -> 0.14 | J14: =J17+Drivers!$C$13 -> 0.1 | K14: =K17+Drivers!$C$13 -> 0.08 | L14: =L17+Drivers!$C$13 -> 0.08 | M14: =M17+Drivers!$C$13 -> 0.08 | N14: =N17+Drivers!$C$13 -> 0.08 | O14: =O17+Drivers!$C$13 -> 0.08 | ... Q14: =Q17+Drivers!$C$13 -> 0.08
B16: Base case
B17: Total Energy and Other | D17: =D7/C7-1 -> 1.1287059 | E17: =E7/D7-1 -> 2.2607975 | F17: =F7/E7-1 -> 0.39143007 | G17: =G7/F7-1 -> 0.27516517 | H17: 0.18 | I17: 0.12 | J17: 0.08 | K17: 0.06 | L17: 0.06 | M17: 0.06 | N17: 0.06 | O17: 0.06 | P17: 0.06 | Q17: 0.06
B19: Worst case
B20: Total Energy and Other | H20: =H17-Drivers!$C$13 -> 0.16 | I20: =I17-Drivers!$C$13 -> 0.1 | J20: =J17-Drivers!$C$13 -> 0.06 | K20: =K17-Drivers!$C$13 -> 0.04 | L20: =L17-Drivers!$C$13 -> 0.04 | M20: =M17-Drivers!$C$13 -> 0.04 | N20: =N17-Drivers!$C$13 -> 0.04 | O20: =O17-Drivers!$C$13 -> 0.04 | ... Q20: =Q17-Drivers!$C$13 -> 0.04

Sheet GP Energy & Other
B1: Gross Profit Energy & Other
C3: Tesla GP% Energy and Other (in mln $)
B4: ($ in million) | C4: 2015 Act | D4: 2016 Act | E4: 2017 Act | F4: 2018 Act | G4: 2019 Act | H4: 2019 Fcst | I4: 2021 Fcst | J4: 2022 Fcst | K4: 2023 Fcst | L4: 2024 Fcst | M4: 2025 Fcst | N4: 2025 Fcst | O4: 2027 Fcst | P4: 2028 Fcst | Q4: 2029 Fcst
B5: Energy generation and storage | C5: =('P&L Input'!C5+'P&L Input'!C9)/1000 -> 2.19 | D5: =('P&L Input'!D5+'P&L Input'!D9)/1000 -> 3.062 | E5: =('P&L Input'!E5+'P&L Input'!E9)/1000 -> 241.728 | F5: =('P&L Input'!F5+'P&L Input'!F9)/1000 -> 190.348 | G5: =('P&L Input'!G5+'P&L Input'!G9)/1000 -> 190 | H5: n.a. | I5: n.a. | J5: n.a. | K5: n.a. | L5: n.a. | M5: n.a. | N5: n.a. | O5: n.a. | P5: n.a. | Q5: n.a.
B6: Services and other | C6: =('P&L Input'!C6+'P&L Input'!C10)/1000 -> 3.642 | D6: =('P&L Input'!D6+'P&L Input'!D10)/1000 -> -4.49 | E6: =('P&L Input'!E6+'P&L Input'!E10)/1000 -> -227.837 | F6: =('P&L Input'!F6+'P&L Input'!F10)/1000 -> -489.313 | G6: =('P&L Input'!G6+'P&L Input'!G10)/1000 -> -544 | H6: n.a. | I6: n.a. | J6: n.a. | K6: n.a. | L6: n.a. | M6: n.a. | N6: n.a. | O6: n.a. | P6: n.a. | Q6: n.a.
B7: Total Energy and Other | C7: =SUM(C5:C6) -> 5.832 | D7: =SUM(D5:D6) -> -1.428 | E7: =SUM(E5:E6) -> 13.891 | F7: =SUM(F5:F6) -> -298.965 | G7: =SUM(G5:G6) -> -354 | H7: =H11*'Revenue Energy & Other'!H7 -> 0 | I7: =I11*'Revenue Energy & Other'!I7 -> 0 | J7: =J11*'Revenue Energy & Other'!J7 -> 0 | K7: =K11*'Revenue Energy & Other'!K7 -> 0 | L7: =L11*'Revenue Energy & Other'!L7 -> 0 | M7: =M11*'Revenue Energy & Other'!M7 -> 0 | N7: =N11*'Revenue Energy & Other'!N7 -> 0 | O7: =O11*'Revenue Energy & Other'!O7 -> 0 | ... Q7: =Q11*'Revenue Energy & Other'!Q7 -> 0
B10: Selected case
B11: Total Energy and Other | C11: =C7/'Revenue Energy & Other'!C7 -> 0.019118052 | D11: =D7/'Revenue Energy & Other'!D7 -> -0.002199068 | E11: =E7/'Revenue Energy & Other'!E7 -> 0.0065602463 | F11: =F7/'Revenue Energy & Other'!F7 -> -0.10147185 | G11: =G7/'Revenue Energy & Other'!G7 -> -0.094224115 | H11: =CHOOSE(Drivers!$C$3,'GP Energy & Other'!H14,'GP Energy & Other'!H17,'GP Energy & Other'!H21) -> 0 | I11: =CHOOSE(Drivers!$C$3,'GP Energy & Other'!I14,'GP Energy & Other'!I17,'GP Energy & Other'!I21) -> 0 | J11: =CHOOSE(Drivers!$C$3,'GP Energy & Other'!J14,'GP Energy & Other'!J17,'GP Energy & Other'!J21) -> 0 | K11: =CHOOSE(Drivers!$C$3,'GP Energy & Other'!K14,'GP Energy & Other'!K17,'GP Energy & Other'!K21) -> 0 | L11: =CHOOSE(Drivers!$C$3,'GP Energy & Other'!L14,'GP Energy & Other'!L17,'GP Energy & Other'!L21) -> 0 | M11: =CHOOSE(Drivers!$C$3,'GP Energy & Other'!M14,'GP Energy & Other'!M17,'GP Energy & Other'!M21) -> 0 | N11: =CHOOSE(Drivers!$C$3,'GP Energy & Other'!N14,'GP Energy & Other'!N17,'GP Energy & Other'!N21) -> 0 | O11: =CHOOSE(Drivers!$C$3,'GP Energy & Other'!O14,'GP Energy & Other'!O17,'GP Energy & Other'!O21) -> 0 | ... Q11: =CHOOSE(Drivers!$C$3,'GP Energy & Other'!Q14,'GP Energy & Other'!Q17,'GP Energy & Other'!Q21) -> 0
B13: GP%
B14: Best case | H14: =H17+Drivers!$C$13 -> 0.02 | I14: =I17+Drivers!$C$13 -> 0.02 | J14: =J17+Drivers!$C$13 -> 0.02 | K14: =K17+Drivers!$C$13 -> 0.02 | L14: =L17+Drivers!$C$13 -> 0.02 | M14: =M17+Drivers!$C$13 -> 0.02 | N14: =N17+Drivers!$C$13 -> 0.02 | O14: =O17+Drivers!$C$13 -> 0.02 | ... Q14: =Q17+Drivers!$C$13 -> 0.02
B15: Total Energy and Other
B17: Base case | H17: 0 | I17: =$H$17 -> 0 | J17: =$H$17 -> 0 | K17: =$H$17 -> 0 | L17: =$H$17 -> 0 | M17: =$H$17 -> 0 | N17: =$H$17 -> 0 | O17: =$H$17 -> 0 | P17: =$H$17 -> 0 | Q17: =$H$17 -> 0
B18: Total Energy and Other
B20: Worst case
B21: Total Energy and Other | H21: =H18-Drivers!$C$13 -> -0.02 | I21: =I18-Drivers!$C$13 -> -0.02 | J21: =J18-Drivers!$C$13 -> -0.02 | K21: =K18-Drivers!$C$13 -> -0.02 | L21: =L18-Drivers!$C$13 -> -0.02 | M21: =M18-Drivers!$C$13 -> -0.02 | N21: =N18-Drivers!$C$13 -> -0.02 | O21: =O18-Drivers!$C$13 -> -0.02 | ... Q21: =Q18-Drivers!$C$13 -> -0.02

Sheet Cost of sales Energy & Other
B1: Cost of sales Energy & Other
C3: Tesla Cost of sales Energy & Other (in mln $)
B4: ($ in million) | C4: 2015 Act | D4: 2016 Act | E4: 2017 Act | F4: 2018 Act | G4: 2019 Act | H4: 2019 Fcst | I4: 2021 Fcst | J4: 2022 Fcst | K4: 2023 Fcst | L4: 2024 Fcst | M4: 2025 Fcst | N4: 2026 Fcst | O4: 2027 Fcst | P4: 2028 Fcst | Q4: 2029 Fcst
B5: Energy generation and storage | C5: =-('Revenue Energy & Other'!C5-'GP Energy & Other'!C5) -> -12.287 | D5: =-('Revenue Energy & Other'!D5-'GP Energy & Other'!D5) -> -178.332 | E5: =-('Revenue Energy & Other'!E5-'GP Energy & Other'!E5) -> -874.538 | F5: =-('Revenue Energy & Other'!F5-'GP Energy & Other'!F5) -> -1364.896 | G5: =-('Revenue Energy & Other'!G5-'GP Energy & Other'!G5) -> -1341 | H5: n.a. | I5: n.a. | J5: n.a. | K5: n.a. | L5: n.a. | M5: n.a. | N5: n.a. | O5: n.a. | P5: n.a. | Q5: n.a.
B6: Services and other | C6: =-('Revenue Energy & Other'!C6-'GP Energy & Other'!C6) -> -286.933 | D6: =-('Revenue Energy & Other'!D6-'GP Energy & Other'!D6) -> -472.462 | E6: =-('Revenue Energy & Other'!E6-'GP Energy & Other'!E6) -> -1229.022 | F6: =-('Revenue Energy & Other'!F6-'GP Energy & Other'!F6) -> -1880.354 | G6: =-('Revenue Energy & Other'!G6-'GP Energy & Other'!G6) -> -2770 | H6: n.a. | I6: n.a. | J6: n.a. | K6: n.a. | L6: n.a. | M6: n.a. | N6: n.a. | O6: n.a. | P6: n.a. | Q6: n.a.
B7: Total Energy and Other | C7: =SUM(C5:C6) -> -299.22 | D7: =SUM(D5:D6) -> -650.794 | E7: =SUM(E5:E6) -> -2103.56 | F7: =SUM(F5:F6) -> -3245.25 | G7: =SUM(G5:G6) -> -4111 | H7: =-('Revenue Energy & Other'!H7-'GP Energy & Other'!H7) -> -4433.26 | I7: =-('Revenue Energy & Other'!I7-'GP Energy & Other'!I7) -> -4965.2512 | J7: =-('Revenue Energy & Other'!J7-'GP Energy & Other'!J7) -> -5362.4713 | K7: =-('Revenue Energy & Other'!K7-'GP Energy & Other'!K7) -> -5684.2196 | L7: =-('Revenue Energy & Other'!L7-'GP Energy & Other'!L7) -> -6025.2727 | M7: =-('Revenue Energy & Other'!M7-'GP Energy & Other'!M7) -> -6386.7891 | N7: =-('Revenue Energy & Other'!N7-'GP Energy & Other'!N7) -> -6769.9965 | O7: =-('Revenue Energy & Other'!O7-'GP Energy & Other'!O7) -> -7176.1962 | ... Q7: =-('Revenue Energy & Other'!Q7-'GP Energy & Other'!Q7) -> -8063.1741

Sheet Operating expenses
B14: Operating expenses

Sheet Opex comparables
B1: Opex comparables
B3: Comparables - 2019
B6: Company | C6: Average | D6: Adj. Average
B7: GM | C7: 0.152 | D7: =C7 -> 0.152
B8: Ford | C8: 0.13234766 | D8: =C8 -> 0.13234766
B9: Fiat Chrysler | C9: 0.093051845 | D9: =C9 -> 0.093051845
B10: BMW | C10: 0.099485177 | D10: =C10 -> 0.099485177
B11: Volkswagen | C11: 0.11 | D11: =C11 -> 0.11
B12: Jaguar | C12: 0.37065334
B13: Porsche | C13: 0.30660065 | D13: =C13 -> 0.30660065
B14: Ferrari | C14: 0.2767445
B15: Scania | C15: 0.15 | D15: =C15 -> 0.15
B16: MAN | C16: 0.15 | D16: =C16 -> 0.15
B17: Paccar | C17: 0.03685738 | D17: =C17 -> 0.03685738
B18: Average | C18: =AVERAGE(C7:C17) -> 0.17070369 | D18: =AVERAGE(D7:D17) -> 0.13670475

Sheet Opex
B1: Opex
C3: Tesla Opex (in mln $)
B4: ($ in million) | C4: 2015 Act | D4: 2016 Act | E4: 2017 Act | F4: 2018 Act | G4: 2019 Act | H4: 2020 Fcst | I4: 2021 Fcst | J4: 2022 Fcst | K4: 2023 Fcst | L4: 2024 Fcst | M4: 2025 Fcst | N4: 2026 Fcst | O4: 2027 Fcst | P4: 2028 Fcst | Q4: 2029 Fcst
B5: Revenues | C5: ='Revenue Energy & Other'!C7+'Revenue automotive'!C11 -> 4046.025 | D5: ='Revenue Energy & Other'!D7+'Revenue automotive'!D11 -> 7000.132 | E5: ='Revenue Energy & Other'!E7+'Revenue automotive'!E11 -> 11758.751 | F5: ='Revenue Energy & Other'!F7+'Revenue automotive'!F11 -> 21461.268 | G5: ='Revenue Energy & Other'!G7+'Revenue automotive'!G11 -> 24578 | H5: ='Revenue Energy & Other'!H7+'Revenue automotive'!H11 -> 37652.43 | I5: ='Revenue Energy & Other'!I7+'Revenue automotive'!I11 -> 49932.934 | J5: ='Revenue Energy & Other'!J7+'Revenue automotive'!J11 -> 67816.248 | ... Q5: ='Revenue Energy & Other'!Q7+'Revenue automotive'!Q11 -> 131530.85
B6: Opex as a % of revenues | C6: =C7/C5 -> -0.40536873 | D6: =D7/D5 -> -0.32379347 | E6: =E7/E5 -> -0.32780463 | F6: =F7/F5 -> -0.20642275 | G6: =G7/G5 -> -0.16836195 | H6: =H10 -> -0.13670475 | I6: =I10 -> -0.13670475 | J6: =J10 -> -0.13670475 | K6: =K10 -> -0.13670475 | L6: =L10 -> -0.13670475 | M6: =M10 -> -0.13670475 | N6: =N10 -> -0.13670475 | O6: =O10 -> -0.13670475 | ... Q6: =Q10 -> -0.13670475
B7: Opex | C7: =('P&L Input'!C12+'P&L Input'!C13+'P&L Input'!C14)/1000 -> -1640.132 | D7: =('P&L Input'!D12+'P&L Input'!D13+'P&L Input'!D14)/1000 -> -2266.597 | E7: =('P&L Input'!E12+'P&L Input'!E13+'P&L Input'!E14)/1000 -> -3854.573 | F7: =('P&L Input'!F12+'P&L Input'!F13+'P&L Input'!F14)/1000 -> -4430.094 | G7: =('P&L Input'!G12+'P&L Input'!G13+'P&L Input'!G14)/1000 -> -4138 | H7: =H5*H6 -> -5147.2658 | I7: =I5*I6 -> -6826.069 | J7: =J5*J6 -> -9270.803 | K7: =K5*K6 -> -11921.681 | L7: =L5*L6 -> -13617.067 | M7: =M5*M6 -> -14576.474 | N7: =N5*N6 -> -15517.943 | O7: =O5*O6 -> -16474.541 | ... Q7: =Q5*Q6 -> -17980.892
B9: Selected case
B10: Opex as a % of revenue | H10: =CHOOSE(Drivers!$C$3,Opex!H14,Opex!H17,Opex!H20) -> -0.13670475 | I10: =CHOOSE(Drivers!$C$3,Opex!I14,Opex!I17,Opex!I20) -> -0.13670475 | J10: =CHOOSE(Drivers!$C$3,Opex!J14,Opex!J17,Opex!J20) -> -0.13670475 | K10: =CHOOSE(Drivers!$C$3,Opex!K14,Opex!K17,Opex!K20) -> -0.13670475 | L10: =CHOOSE(Drivers!$C$3,Opex!L14,Opex!L17,Opex!L20) -> -0.13670475 | M10: =CHOOSE(Drivers!$C$3,Opex!M14,Opex!M17,Opex!M20) -> -0.13670475 | N10: =CHOOSE(Drivers!$C$3,Opex!N14,Opex!N17,Opex!N20) -> -0.13670475 | O10: =CHOOSE(Drivers!$C$3,Opex!O14,Opex!O17,Opex!O20) -> -0.13670475 | ... Q10: =CHOOSE(Drivers!$C$3,Opex!Q14,Opex!Q17,Opex!Q20) -> -0.13670475
B12: Opex %
B13: Best case
B14: Opex as a % of revenue | H14: =H17+2% -> -0.11670475 | I14: =I17+2% -> -0.11670475 | J14: =J17+2% -> -0.11670475 | K14: =K17+2% -> -0.11670475 | L14: =L17+2% -> -0.11670475 | M14: =M17+2% -> -0.11670475 | N14: =N17+2% -> -0.11670475 | O14: =O17+2% -> -0.11670475 | ... Q14: =Q17+2% -> -0.11670475
B16: Base case
B17: Opex as a % of revenue | H17: =-'Opex comparables'!$D$18 -> -0.13670475 | I17: =-'Opex comparables'!$D$18 -> -0.13670475 | J17: =-'Opex comparables'!$D$18 -> -0.13670475 | K17: =-'Opex comparables'!$D$18 -> -0.13670475 | L17: =-'Opex comparables'!$D$18 -> -0.13670475 | M17: =-'Opex comparables'!$D$18 -> -0.13670475 | N17: =-'Opex comparables'!$D$18 -> -0.13670475 | O17: =-'Opex comparables'!$D$18 -> -0.13670475 | ... Q17: =-'Opex comparables'!$D$18 -> -0.13670475
B19: Worst case
B20: Opex as a % of revenue | H20: =H17-2% -> -0.15670475 | I20: =I17-2% -> -0.15670475 | J20: =J17-2% -> -0.15670475 | K20: =K17-2% -> -0.15670475 | L20: =L17-2% -> -0.15670475 | M20: =M17-2% -> -0.15670475 | N20: =N17-2% -> -0.15670475 | O20: =O17-2% -> -0.15670475 | ... Q20: =Q17-2% -> -0.15670475

Sheet Balance Sheet -->
B14: Balance Sheet -->

Sheet PP&E -->
B14: Property, Plant & Equipment

Sheet PP&E
B1: Fixed asset roll forward
B3: ="Selected case:"&CHOOSE(C3," as a % of PPE"," as a % of revenue") -> Selected case: as a % of PPE | C3: 1
C5: Tesla PP&E (in mln $)
B6: ($ in million) | C6: 31Dec2015 Act | D6: 31Dec2016 Act | E6: 31Dec2017 Act | F6: 31Dec2018 Act | G6: 31Dec2019 Act | H6: 31Dec2020 Fcst | I6: 31Dec2021 Fcst | J6: 31Dec2022 Fcst | K6: 31Dec2023 Fcst | L6: 31Dec2024 Fcst | M6: 31Dec2025 Fcst | N6: 31Dec2026 Fcst | O6: 31Dec2027 Fcst | P6: 31Dec2028 Fcst | Q6: 31Dec2029 Fcst
B7: Beginning PP&E | C7: =738494/1000 -> 738.494 | D7: =C10 -> 3403.334 | E7: =D10 -> 5982.957 | F7: =E10 -> 10027.522 | G7: =F10 -> 11330.077 | H7: =G10 -> 10396 | I7: =H10 -> 11620.915 | J7: =I10 -> 12861.036 | K7: =J10 -> 14090.027 | ... Q7: =P10 -> 18899.515
B8: Capex | C8: =C10-C7-C9 -> 3087.84 | D8: =D10-D7-D9 -> 3526.623 | E8: =E10-E7-E9 -> 5680.565 | F8: =F10-F7-F9 -> 3203.555 | G8: =G10-G7-G9 -> 1219.923 | H8: =CHOOSE($C$3,H32*H7,H33*Opex!H5) -> 2516.128 | I8: =CHOOSE($C$3,I32*I7,I33*Opex!I5) -> 2812.5924 | J8: =CHOOSE($C$3,J32*J7,J33*Opex!J5) -> 3112.7368 | K8: =CHOOSE($C$3,K32*K7,K33*Opex!K5) -> 3410.1876 | L8: =CHOOSE($C$3,L32*L7,L33*Opex!L5) -> 3697.0938 | M8: =CHOOSE($C$3,M32*M7,M33*Opex!M5) -> 3963.9592 | N8: =CHOOSE($C$3,N32*N7,N33*Opex!N5) -> 4199.4745 | O8: =CHOOSE($C$3,O32*O7,O33*Opex!O5) -> 4390.3521 | ... Q8: =CHOOSE($C$3,Q32*Q7,Q33*Opex!Q5) -> 4574.2208
B9: D&A | C9: -423 | D9: -947 | E9: -1636 | F9: -1901 | G9: -2154 | H9: =H28 -> -1291.2128 | I9: =I28 -> -1572.472 | J9: =J28 -> -1883.7457 | K9: =K28 -> -2224.7645 | L9: =L28 -> -2594.4739 | M9: =M28 -> -2990.8698 | N9: =N28 -> -3410.8172 | O9: =O28 -> -3849.8524 | ... Q9: =Q28 -> -4759.3913
B10: Ending PP&E | C10: ='Balance Sheet Input'!C12/1000 -> 3403.334 | D10: ='Balance Sheet Input'!D12/1000 -> 5982.957 | E10: ='Balance Sheet Input'!E12/1000 -> 10027.522 | F10: ='Balance Sheet Input'!F12/1000 -> 11330.077 | G10: ='Balance Sheet Input'!G12/1000 -> 10396 | H10: =SUM(H7:H9) -> 11620.915 | I10: =SUM(I7:I9) -> 12861.036 | J10: =SUM(J7:J9) -> 14090.027 | K10: =SUM(K7:K9) -> 15275.45 | L10: =SUM(L7:L9) -> 16378.07 | M10: =SUM(M7:M9) -> 17351.159 | N10: =SUM(N7:N9) -> 18139.816 | O10: =SUM(O7:O9) -> 18680.316 | ... Q10: =SUM(Q7:Q9) -> 18714.345
B12: Useful life Capex | C12: 10
B13: Useful life historical assets | C13: 10
C15: Tesla D&A (in mln $)
B16: ($ in million) | C16: 31Dec2015 Act | D16: 31Dec2016 Act | E16: 31Dec2017 Act | F16: 31Dec2018 Act | G16: 31Dec2019 Act | H16: 31Dec2020 Fcst | I16: 31Dec2021 Fcst | J16: 31Dec2022 Fcst | K16: 31Dec2023 Fcst | L16: 31Dec2024 Fcst | M16: 31Dec2025 Fcst | N16: 31Dec2026 Fcst | O16: 31Dec2027 Fcst | P16: 31Dec2028 Fcst | Q16: 31Dec2029 Fcst
H17: =-$H$7/$C$13 -> -1039.6 | I17: =-$H$7/$C$13 -> -1039.6 | J17: =-$H$7/$C$13 -> -1039.6 | K17: =-$H$7/$C$13 -> -1039.6 | L17: =-$H$7/$C$13 -> -1039.6 | M17: =-$H$7/$C$13 -> -1039.6 | N17: =-$H$7/$C$13 -> -1039.6 | O17: =-$H$7/$C$13 -> -1039.6 | ... Q17: =-$H$7/$C$13 -> -1039.6
H18: =-$H$8/$C$13 -> -251.6128 | I18: =-$H$8/$C$13 -> -251.6128 | J18: =-$H$8/$C$13 -> -251.6128 | K18: =-$H$8/$C$13 -> -251.6128 | L18: =-$H$8/$C$13 -> -251.6128 | M18: =-$H$8/$C$13 -> -251.6128 | N18: =-$H$8/$C$13 -> -251.6128 | O18: =-$H$8/$C$13 -> -251.6128 | ... Q18: =-$H$8/$C$13 -> -251.6128
I19: =-$I$8/$C$12 -> -281.25924 | J19: =-$I$8/$C$12 -> -281.25924 | K19: =-$I$8/$C$12 -> -281.25924 | L19: =-$I$8/$C$12 -> -281.25924 | M19: =-$I$8/$C$12 -> -281.25924 | N19: =-$I$8/$C$12 -> -281.25924 | O19: =-$I$8/$C$12 -> -281.25924 | P19: =-$I$8/$C$12 -> -281.25924 | Q19: =-$I$8/$C$12 -> -281.25924
J20: =-$J$8/$C$13 -> -311.27368 | K20: =-$J$8/$C$13 -> -311.27368 | L20: =-$J$8/$C$13 -> -311.27368 | M20: =-$J$8/$C$13 -> -311.27368 | N20: =-$J$8/$C$13 -> -311.27368 | O20: =-$J$8/$C$13 -> -311.27368 | P20: =-$J$8/$C$13 -> -311.27368 | Q20: =-$J$8/$C$13 -> -311.27368
K21: =-$K$8/$C$12 -> -341.01876 | L21: =-$K$8/$C$12 -> -341.01876 | M21: =-$K$8/$C$12 -> -341.01876 | N21: =-$K$8/$C$12 -> -341.01876 | O21: =-$K$8/$C$12 -> -341.01876 | P21: =-$K$8/$C$12 -> -341.01876 | Q21: =-$K$8/$C$12 -> -341.01876
L22: =-$L$8/$C$12 -> -369.70938 | M22: =-$L$8/$C$12 -> -369.70938 | N22: =-$L$8/$C$12 -> -369.70938 | O22: =-$L$8/$C$12 -> -369.70938 | P22: =-$L$8/$C$12 -> -369.70938 | Q22: =-$L$8/$C$12 -> -369.70938
M23: =-$M$8/$C$12 -> -396.39592 | N23: =-$M$8/$C$12 -> -396.39592 | O23: =-$M$8/$C$12 -> -396.39592 | P23: =-$M$8/$C$12 -> -396.39592 | Q23: =-$M$8/$C$12 -> -396.39592
N24: =-$N$8/$C$12 -> -419.94745 | O24: =-$N$8/$C$12 -> -419.94745 | P24: =-$N$8/$C$12 -> -419.94745 | Q24: =-$N$8/$C$12 -> -419.94745
O25: =-$O$8/$C$12 -> -439.03521 | P25: =-$O$8/$C$12 -> -439.03521 | Q25: =-$O$8/$C$12 -> -439.03521
P26: =-$P$8/$C$12 -> -452.11684 | Q26: =-$P$8/$C$12 -> -452.11684
Q27: =-$Q$8/$C$12 -> -457.42208
B28: Total D&A | C28: =SUM(C17:C27) -> 0 | D28: =SUM(D17:D27) -> 0 | E28: =SUM(E17:E27) -> 0 | F28: =SUM(F17:F27) -> 0 | G28: =SUM(G17:G27) -> 0 | H28: =SUM(H17:H27) -> -1291.2128 | I28: =SUM(I17:I27) -> -1572.472 | J28: =SUM(J17:J27) -> -1883.7457 | ... Q28: =SUM(Q17:Q27) -> -4759.3913
B31: Selected case
B32: Capex as a % of PP&E | H32: =CHOOSE(Drivers!$C$3,H36,H39,H42) -> 0.24202847 | I32: =CHOOSE(Drivers!$C$3,I36,I39,I42) -> 0.24202847 | J32: =CHOOSE(Drivers!$C$3,J36,J39,J42) -> 0.24202847 | K32: =CHOOSE(Drivers!$C$3,K36,K39,K42) -> 0.24202847 | L32: =CHOOSE(Drivers!$C$3,L36,L39,L42) -> 0.24202847 | M32: =CHOOSE(Drivers!$C$3,M36,M39,M42) -> 0.24202847 | N32: =CHOOSE(Drivers!$C$3,N36,N39,N42) -> 0.24202847 | O32: =CHOOSE(Drivers!$C$3,O36,O39,O42) -> 0.24202847 | ... Q32: =CHOOSE(Drivers!$C$3,Q36,Q39,Q42) -> 0.24202847
B33: Capex as a % of revenue | H33: =CHOOSE(Drivers!$C$3,H37,H40,H43) -> 0.064053331 | I33: =CHOOSE(Drivers!$C$3,I37,I40,I43) -> 0.064053331 | J33: =CHOOSE(Drivers!$C$3,J37,J40,J43) -> 0.064053331 | K33: =CHOOSE(Drivers!$C$3,K37,K40,K43) -> 0.064053331 | L33: =CHOOSE(Drivers!$C$3,L37,L40,L43) -> 0.064053331 | M33: =CHOOSE(Drivers!$C$3,M37,M40,M43) -> 0.064053331 | N33: =CHOOSE(Drivers!$C$3,N37,N40,N43) -> 0.064053331 | O33: =CHOOSE(Drivers!$C$3,O37,O40,O43) -> 0.064053331 | ... Q33: =CHOOSE(Drivers!$C$3,Q37,Q40,Q43) -> 0.064053331
B34: Capex %
B35: Best case
B36: Capex as a % of PP&E | H36: =H39-5% -> 0.19202847 | I36: =I39-5% -> 0.19202847 | J36: =J39-5% -> 0.19202847 | K36: =K39-5% -> 0.19202847 | L36: =L39-5% -> 0.19202847 | M36: =M39-5% -> 0.19202847 | N36: =N39-5% -> 0.19202847 | O36: =O39-5% -> 0.19202847 | P36: =P39-5% -> 0.19202847 | Q36: =Q39+5% -> 0.29202847
B37: =B33 -> Capex as a % of revenue | H37: =H40-3% -> 0.034053331 | I37: =I40-3% -> 0.034053331 | J37: =J40-3% -> 0.034053331 | K37: =K40-3% -> 0.034053331 | L37: =L40-3% -> 0.034053331 | M37: =M40-3% -> 0.034053331 | N37: =N40-3% -> 0.034053331 | O37: =O40-3% -> 0.034053331 | P37: =P40-3% -> 0.034053331 | Q37: =Q40+3% -> 0.094053331
B38: Base case
B39: Capex as a % of PP&E | H39: =-'PP&E Comparables'!D16 -> 0.24202847 | I39: =H39 -> 0.24202847 | J39: =I39 -> 0.24202847 | K39: =J39 -> 0.24202847 | L39: =K39 -> 0.24202847 | M39: =L39 -> 0.24202847 | N39: =M39 -> 0.24202847 | O39: =N39 -> 0.24202847 | P39: =O39 -> 0.24202847 | Q39: =P39 -> 0.24202847
B40: =B33 -> Capex as a % of revenue | H40: =-'PP&E Comparables'!G16 -> 0.064053331 | I40: =H40 -> 0.064053331 | J40: =I40 -> 0.064053331 | K40: =J40 -> 0.064053331 | L40: =K40 -> 0.064053331 | M40: =L40 -> 0.064053331 | N40: =M40 -> 0.064053331 | O40: =N40 -> 0.064053331 | P40: =O40 -> 0.064053331 | Q40: =P40 -> 0.064053331
B41: Worst case
B42: Capex as a % of PP&E | H42: =H39+5% -> 0.29202847 | I42: =I39+5% -> 0.29202847 | J42: =J39+5% -> 0.29202847 | K42: =K39+5% -> 0.29202847 | L42: =L39+5% -> 0.29202847 | M42: =M39+5% -> 0.29202847 | N42: =N39+5% -> 0.29202847 | O42: =O39+5% -> 0.29202847 | P42: =P39+5% -> 0.29202847 | Q42: =Q39-5% -> 0.19202847
B43: =B33 -> Capex as a % of revenue | H43: =H40+3% -> 0.094053331 | I43: =I40+3% -> 0.094053331 | J43: =J40+3% -> 0.094053331 | K43: =K40+3% -> 0.094053331 | L43: =L40+3% -> 0.094053331 | M43: =M40+3% -> 0.094053331 | N43: =N40+3% -> 0.094053331 | O43: =O40+3% -> 0.094053331 | P43: =P40+3% -> 0.094053331 | Q43: =Q40-3% -> 0.034053331

Sheet PP&E Comparables
B1: PP&E comparables
B3: Comparables - 2019
C5: CAPEX as a % of PP&E | F5: CAPEX as a % of revenues
B6: Company | C6: Average | D6: Adj. Average | F6: Average | G6: Adj. Average
B7: GM | C7: -0.19592258 | D7: =C7 -> -0.19592258 | F7: -0.055320358 | G7: =F7 -> -0.055320358
B8: Ford | C8: -0.21112278 | D8: =C8 -> -0.21112278 | F8: -0.048992944 | G8: =F8 -> -0.048992944
B9: Fiat Chrysler | C9: -0.29309983 | D9: =C9 -> -0.29309983 | F9: -0.077504691 | G9: =F9 -> -0.077504691
B10: BMW | C10: -0.29601301 | D10: =C10 -> -0.29601301 | F10: -0.073449532 | G10: =F10 -> -0.073449532
B11: Mercedes | C11: -0.19381849 | D11: =C11 -> -0.19381849 | F11: -0.041674144 | G11: =F11 -> -0.041674144
B12: Volkswagen | C12: -0.21511065 | D12: =C12 -> -0.21511065 | F12: -0.056326989 | G12: =F12 -> -0.056326989
B13: Jaguar | C13: -0.24491682 | D13: =C13 -> -0.24491682 | F13: -0.065664492 | G13: =F13 -> -0.065664492
B14: Ferrari | C14: -0.32922296 | D14: =C14 -> -0.32922296 | F14: -0.093493495 | G14: =F14 -> -0.093493495
B15: Paccar | C15: -0.19902913 | D15: =C15 -> -0.19902913 | F15: -0.023797678
B16: Average | C16: =AVERAGE(C7:C15) -> -0.24202847 | D16: =AVERAGE(D7:D15) -> -0.24202847 | F16: =AVERAGE(F7:F15) -> -0.05958048 | G16: =AVERAGE(G7:G15) -> -0.064053331

Sheet Working Capital --> 
B14: Working capital

Sheet WC comparables
B1: Working Capital comparables
B3: Comparables - 2019
C5: DSO | F5: DIO | I5: DPO | L5: Net trade cycle
B6: Vehicle | C6: Average | D6: Adj. Average | F6: Average | G6: Adj. Average | I6: Average | J6: Adj. Average | L6: Average | M6: Adj. Average
B7: GM | C7: 19.942786 | D7: =C7 -> 19.942786 | F7: 33.829608 | G7: =F7 -> 33.829608 | I7: 68.381488 | J7: =I7 -> 68.381488 | L7: =C7+F7-I7 -> -14.609093 | M7: =L7 -> -14.609093
B8: Ford | C8: 25.851187 | D8: =C8 -> 25.851187 | F8: 29.988195 | G8: =F8 -> 29.988195 | I8: 57.517466 | J8: =I8 -> 57.517466 | L8: =C8+F8-I8 -> -1.6780836 | M8: =L8 -> -1.6780836
B9: Fiat Chrysler | C9: 22.055145 | D9: =C9 -> 22.055145 | F9: 37.567301 | G9: =F9 -> 37.567301 | I9: 83.527543 | J9: =I9 -> 83.527543 | L9: =C9+F9-I9 -> -23.905097 | M9: =L9 -> -23.905097
B10: BMW | C10: 8.7485003 | D10: =C10 -> 8.7485003 | F10: 66.427199 | G10: =F10 -> 66.427199 | I10: 40.64769 | J10: =I10 -> 40.64769 | L10: =C10+F10-I10 -> 34.528009 | M10: =L10 -> 34.528009
B11: Volkswagen | C11: 25.565882 | D11: =C11 -> 25.565882 | F11: 82.692614 | G11: =F11 -> 82.692614 | I11: 40.238832 | J11: =I11 -> 40.238832 | L11: =C11+F11-I11 -> 68.019664 | M11: =L11 -> 68.019664
B12: Jaguar | C12: 20.249442 | F12: 82.889598 | I12: 162.72368 | L12: =C12+F12-I12 -> -59.584635
B13: Ferrari | C13: 22.081784 | D13: =C13 -> 22.081784 | F13: 83.767313 | G13: =F13 -> 83.767313 | I13: 142.00554 | J13: =I13 -> 142.00554 | L13: =C13+F13-I13 -> -36.156443 | M13: =L13 -> -36.156443
B14: Paccar | C14: 19.492537 | D14: =C14 -> 19.492537 | F14: 20.192644 | G14: =F14 -> 20.192644 | I14: 55.936953 | J14: =I14 -> 55.936953 | L14: =C14+F14-I14 -> -16.251771 | M14: =D14+G14-J14 -> -16.251771
B15: Average | C15: =AVERAGE(C7:C14) -> 20.498408 | D15: =AVERAGE(D7:D14) -> 20.533975 | F15: =AVERAGE(F7:F14) -> 54.669309 | G15: =AVERAGE(G7:G14) -> 50.637839 | I15: =AVERAGE(I7:I14) -> 81.372398 | J15: =AVERAGE(J7:J14) -> 69.750787 | L15: =AVERAGE(L7:L14) -> -6.2046813 | M15: =AVERAGE(M7:M14) -> 1.4210264

Sheet Working capital
B1: Working capital
C3: Tesla Working capital (in mln $)
B4: ($ in million) | C4: 31Dec2015 Act | D4: 31Dec2016 Act | E4: 31Dec2017 Act | F4: 31Dec2018 Act | G4: 31Dec2019 Act | H4: 31Dec2020 Fcst | I4: 31Dec2021 Fcst | J4: 31Dec2022 Fcst | K4: 31Dec2023 Fcst | L4: 31Dec2024 Fcst | M4: 31Dec2025 Fcst | N4: 31Dec2026 Fcst | O4: 31Dec2027 Fcst | P4: 31Dec2028 Fcst | Q4: 31Dec2029 Fcst
B5: Trade receivables | C5: ='Balance Sheet Input'!C6/1000 -> 168.965 | D5: ='Balance Sheet Input'!D6/1000 -> 499.142 | E5: ='Balance Sheet Input'!E6/1000 -> 515.381 | F5: ='Balance Sheet Input'!F6/1000 -> 949.022 | G5: ='Balance Sheet Input'!G6/1000 -> 1324 | H5: =H11*('P&L'!H5)/360 -> 1920.1572 | I5: =I11*('P&L'!I5)/360 -> 2546.4248 | J5: =J11*('P&L'!J5)/360 -> 3458.4184 | K5: =K11*('P&L'!K5)/360 -> 4447.3127 | L5: =L11*('P&L'!L5)/360 -> 5079.7666 | M5: =M11*('P&L'!M5)/360 -> 5437.6679 | N5: =N11*('P&L'!N5)/360 -> 5788.8771 | O5: =O11*('P&L'!O5)/360 -> 6145.7305 | ... Q5: =Q11*('P&L'!Q5)/360 -> 6707.6658
B6: Inventory | C6: ='Balance Sheet Input'!C7/1000 -> 1277.838 | D6: ='Balance Sheet Input'!D7/1000 -> 2067.454 | E6: ='Balance Sheet Input'!E7/1000 -> 2263.537 | F6: ='Balance Sheet Input'!F7/1000 -> 3113.446 | G6: ='Balance Sheet Input'!G7/1000 -> 3552 | H6: =-H12*('P&L'!H$6)/360 -> 8353.4109 | I6: =-I12*('P&L'!I$6)/360 -> 11184.361 | J6: =-J12*('P&L'!J$6)/360 -> 15256.687 | K6: =-K12*('P&L'!K$6)/360 -> 19680.056 | L6: =-L12*('P&L'!L$6)/360 -> 22463.324 | M6: =-M12*('P&L'!M$6)/360 -> 24063.439 | N6: =-N12*('P&L'!N$6)/360 -> 25630.801 | O6: =-O12*('P&L'!O$6)/360 -> 27225.903 | ... Q6: =-Q12*('P&L'!Q$6)/360 -> 29727.142
B7: Trade payables | C7: ='Balance Sheet Input'!C19/1000 -> 916.148 | D7: ='Balance Sheet Input'!D19/1000 -> 1860.341 | E7: ='Balance Sheet Input'!E19/1000 -> 2390.25 | F7: ='Balance Sheet Input'!F19/1000 -> 3404.451 | G7: ='Balance Sheet Input'!G19/1000 -> 3771 | H7: =-H13*('P&L'!H$6)/360 -> 7666.976 | I7: =-I13*('P&L'!I$6)/360 -> 10265.295 | J7: =-J13*('P&L'!J$6)/360 -> 14002.981 | K7: =-K13*('P&L'!K$6)/360 -> 18062.863 | L7: =-L13*('P&L'!L$6)/360 -> 20617.418 | M7: =-M13*('P&L'!M$6)/360 -> 22086.045 | N7: =-N13*('P&L'!N$6)/360 -> 23524.61 | O7: =-O13*('P&L'!O$6)/360 -> 24988.636 | ... Q7: =-Q13*('P&L'!Q$6)/360 -> 27284.338
B8: Net trade cycle | C8: =C5+C6-C7 -> 530.655 | D8: =D5+D6-D7 -> 706.255 | E8: =E5+E6-E7 -> 388.668 | F8: =F5+F6-F7 -> 658.017 | G8: =G5+G6-G7 -> 1105 | H8: =H5+H6-H7 -> 2606.5922 | I8: =I5+I6-I7 -> 3465.4909 | J8: =J5+J6-J7 -> 4712.1247 | ... Q8: =Q5+Q6-Q7 -> 9150.4703
B10: Selected case:
B11: DSO | C11: ='Balance Sheet Input'!C40 -> 15.033867 | D11: ='Balance Sheet Input'!D40 -> 25.669676 | E11: ='Balance Sheet Input'!E40 -> 15.778645 | F11: ='Balance Sheet Input'!F40 -> 15.919279 | G11: ='Balance Sheet Input'!G40 -> 19.392953 | H11: =AVERAGE($C11:$G11) -> 18.358884 | I11: =AVERAGE($C11:$G11) -> 18.358884 | J11: =AVERAGE($C11:$G11) -> 18.358884 | K11: =AVERAGE($C11:$G11) -> 18.358884 | L11: =AVERAGE($C11:$G11) -> 18.358884 | M11: =AVERAGE($C11:$G11) -> 18.358884 | N11: =AVERAGE($C11:$G11) -> 18.358884 | O11: =AVERAGE($C11:$G11) -> 18.358884 | ... Q11: =AVERAGE($C11:$G11) -> 18.358884
B12: DIO | C12: ='Balance Sheet Input'!C41 -> 147.32376 | D12: ='Balance Sheet Input'!D41 -> 137.80794 | E12: ='Balance Sheet Input'!E41 -> 85.449954 | F12: ='Balance Sheet Input'!F41 -> 64.344949 | G12: ='Balance Sheet Input'!G41 -> 62.349213 | H12: =AVERAGE($C12:$G12) -> 99.455162 | I12: =AVERAGE($C12:$G12) -> 99.455162 | J12: =AVERAGE($C12:$G12) -> 99.455162 | K12: =AVERAGE($C12:$G12) -> 99.455162 | L12: =AVERAGE($C12:$G12) -> 99.455162 | M12: =AVERAGE($C12:$G12) -> 99.455162 | N12: =AVERAGE($C12:$G12) -> 99.455162 | O12: =AVERAGE($C12:$G12) -> 99.455162 | ... Q12: =AVERAGE($C12:$G12) -> 99.455162
B13: DPO | C13: ='Balance Sheet Input'!C42 -> 105.62401 | D13: ='Balance Sheet Input'!D42 -> 124.00264 | E13: ='Balance Sheet Input'!E42 -> 90.23345 | F13: ='Balance Sheet Input'!F42 -> 70.35909 | G13: ='Balance Sheet Input'!G42 -> 66.193379 | H13: =AVERAGE($C13:$G13) -> 91.282513 | I13: =AVERAGE($C13:$G13) -> 91.282513 | J13: =AVERAGE($C13:$G13) -> 91.282513 | K13: =AVERAGE($C13:$G13) -> 91.282513 | L13: =AVERAGE($C13:$G13) -> 91.282513 | M13: =AVERAGE($C13:$G13) -> 91.282513 | N13: =AVERAGE($C13:$G13) -> 91.282513 | O13: =AVERAGE($C13:$G13) -> 91.282513 | ... Q13: =AVERAGE($C13:$G13) -> 91.282513
B14: Net trade cycle | C14: =C11+C12-C13 -> 56.733621 | D14: =D11+D12-D13 -> 39.474972 | E14: =E11+E12-E13 -> 10.995149 | F14: =F11+F12-F13 -> 9.9051388 | G14: =G11+G12-G13 -> 15.548787 | H14: =H11+H12-H13 -> 26.531534 | I14: =I11+I12-I13 -> 26.531534 | J14: =J11+J12-J13 -> 26.531534 | ... Q14: =Q11+Q12-Q13 -> 26.531534

Sheet WC development

Sheet Financing -->
B14: Financing

Sheet Financing
B1: Financing
B3: Cover negative cash flows with:
B4: Debt | C4: 0.5
B5: Equity | C5: 0.5
B7: Bond Yield as of Sep. 20 | C7: =Drivers!C11 -> 0.04324
C9: Tesla Financing (in mln $)
B10: ($ in million) | C10: 31Dec2015 Act | D10: 31Dec2016 Act | E10: 31Dec2017 Act | F10: 31Dec2018 Act | G10: 31Dec2019 Act | H10: 31Dec2020 Fcst | I10: 31Dec2021 Fcst | J10: 31Dec2022 Fcst | K10: 31Dec2023 Fcst | L10: 31Dec2024 Fcst | M10: 31Dec2025 Fcst | N10: 31Dec2026 Fcst | O10: 31Dec2027 Fcst | P10: 31Dec2028 Fcst | Q10: 31Dec2029 Fcst
B11: Long-term debt and capital leases, net of current | C11: ='Balance Sheet Input'!C29/1000 -> 2021.093 | D11: ='Balance Sheet Input'!D29/1000 -> 5860.049 | E11: ='Balance Sheet Input'!E29/1000 -> 9415.7 | F11: ='Balance Sheet Input'!F29/1000 -> 9403.672 | G11: ='Balance Sheet Input'!G29/1000 -> 11634
B12: ='P&L Input'!B17 -> Interest expense | C12: ='P&L Input'!C17/1000 -> -118.851 | D12: ='P&L Input'!D17/1000 -> -198.81 | E12: ='P&L Input'!E17/1000 -> -471.259 | F12: ='P&L Input'!F17/1000 -> -663.071 | G12: ='P&L Input'!G17/1000 -> -685
B13: Interest rate | C13: =C12/C11 -> -0.05880531 | D13: =D12/D11 -> -0.033926337 | E13: =E12/E11 -> -0.050050341 | F13: =F12/F11 -> -0.070511923 | G13: =G12/G11 -> -0.058879147
C16: Tesla Cash Flow (in mln $)
C17: 2014 Act | D17: 2015 Act | E17: 2016 Act | F17: 2017 Act | G17: 2018 H1 Act | H17: 2019 Fcst | I17: 2020 Fcst | J17: 2021 Fcst | K17: 2022 Fcst | L17: 2023 Fcst | M17: 2024 Fcst | N17: 2025 Fcst | O17: 2026 Fcst | P17: 2027 Fcst | Q17: 2028 Fcst
B18: Unlevered Free Cash Flow
B19: Debt
B20: Equity

Sheet Output -->
B14: Output -->

Sheet P&L
B1: P&L
C3: Tesla P&L (in mln $)
B4: ($ in million) | C4: 2015 Act | D4: 2016 Act | E4: 2017 Act | F4: 2018 Act | G4: 2019 Act | H4: 2020 Fcst | I4: 2021 Fcst | J4: 2022 Fcst | K4: 2023 Fcst | L4: 2024 Fcst | M4: 2025 Fcst | N4: 2026 Fcst | O4: 2027 Fcst | P4: 2028 Fcst | Q4: 2029 Fcst
B5: Revenues | C5: ='Revenue automotive'!C11+'Revenue Energy & Other'!C7 -> 4046.025 | D5: ='Revenue automotive'!D11+'Revenue Energy & Other'!D7 -> 7000.132 | E5: ='Revenue automotive'!E11+'Revenue Energy & Other'!E7 -> 11758.751 | F5: ='Revenue automotive'!F11+'Revenue Energy & Other'!F7 -> 21461.268 | G5: ='Revenue automotive'!G11+'Revenue Energy & Other'!G7 -> 24578 | H5: ='Revenue automotive'!H11+'Revenue Energy & Other'!H7 -> 37652.43 | I5: ='Revenue automotive'!I11+'Revenue Energy & Other'!I7 -> 49932.934 | J5: ='Revenue automotive'!J11+'Revenue Energy & Other'!J7 -> 67816.248 | ... Q5: ='Revenue automotive'!Q11+'Revenue Energy & Other'!Q7 -> 131530.85
B6: Cost of sales | C6: ='Cost of sales Energy & Other'!C7+'Cost of sales automotive'!C11 -> -3122.522 | D6: ='Cost of sales Energy & Other'!D7+'Cost of sales automotive'!D11 -> -5400.875 | E6: ='Cost of sales Energy & Other'!E7+'Cost of sales automotive'!E11 -> -9536.264 | F6: ='Cost of sales Energy & Other'!F7+'Cost of sales automotive'!F11 -> -17419.247 | G6: ='Cost of sales Energy & Other'!G7+'Cost of sales automotive'!G11 -> -20509 | H6: ='Cost of sales Energy & Other'!H7+'Cost of sales automotive'!H11 -> -30237.022 | I6: ='Cost of sales Energy & Other'!I7+'Cost of sales automotive'!I11 -> -40484.272 | J6: ='Cost of sales Energy & Other'!J7+'Cost of sales automotive'!J11 -> -55224.959 | ... Q6: ='Cost of sales Energy & Other'!Q7+'Cost of sales automotive'!Q11 -> -107603.98
B7: Gross profit | C7: =SUM(C5:C6) -> 923.503 | D7: =SUM(D5:D6) -> 1599.257 | E7: =SUM(E5:E6) -> 2222.487 | F7: =SUM(F5:F6) -> 4042.021 | G7: =SUM(G5:G6) -> 4069 | H7: =SUM(H5:H6) -> 7415.4077 | I7: =SUM(I5:I6) -> 9448.662 | J7: =SUM(J5:J6) -> 12591.289 | ... Q7: =SUM(Q5:Q6) -> 23926.875
B8: Operating expenses | C8: =Opex!C7 -> -1640.132 | D8: =Opex!D7 -> -2266.597 | E8: =Opex!E7 -> -3854.573 | F8: =Opex!F7 -> -4430.094 | G8: =Opex!G7 -> -4138 | H8: =Opex!H7 -> -5147.2658 | I8: =Opex!I7 -> -6826.069 | J8: =Opex!J7 -> -9270.803 | ... Q8: =Opex!Q7 -> -17980.892
B9: EBIT | C9: =SUM(C7:C8) -> -716.629 | D9: =SUM(D7:D8) -> -667.34 | E9: =SUM(E7:E8) -> -1632.086 | F9: =SUM(F7:F8) -> -388.073 | G9: =SUM(G7:G8) -> -69 | H9: =SUM(H7:H8) -> 2268.1419 | I9: =SUM(I7:I8) -> 2622.593 | J9: =SUM(J7:J8) -> 3320.4859 | ... Q9: =SUM(Q7:Q8) -> 5945.983
B10: Interest expenses/income | C10: =Financing!C12+('P&L Input'!C16+'P&L Input'!C18)/1000 -> -158.995 | D10: =Financing!D12+('P&L Input'!D16+'P&L Input'!D18)/1000 -> -79.008 | E10: =Financing!E12+('P&L Input'!E16+'P&L Input'!E18)/1000 -> -576.946 | F10: =Financing!F12+('P&L Input'!F16+'P&L Input'!F18)/1000 -> -616.672 | G10: =Financing!G12+('P&L Input'!G16+'P&L Input'!G18)/1000 -> -596 | H10: =Financing!H12 -> 0 | I10: =Financing!I12 -> 0 | J10: =Financing!J12 -> 0 | K10: =Financing!K12 -> 0 | L10: =Financing!L12 -> 0 | M10: =Financing!M12 -> 0 | N10: =Financing!N12 -> 0 | O10: =Financing!O12 -> 0 | ... Q10: =Financing!Q12 -> 0
B11: EBT | C11: =SUM(C9:C10) -> -875.624 | D11: =SUM(D9:D10) -> -746.348 | E11: =SUM(E9:E10) -> -2209.032 | F11: =SUM(F9:F10) -> -1004.745 | G11: =SUM(G9:G10) -> -665 | H11: =SUM(H9:H10) -> 2268.1419 | I11: =SUM(I9:I10) -> 2622.593 | J11: =SUM(J9:J10) -> 3320.4859 | ... Q11: =SUM(Q9:Q10) -> 5945.983
B12: Taxes | C12: ='P&L Input'!C20/1000 -> -13.039 | D12: ='P&L Input'!D20/1000 -> -26.698 | E12: ='P&L Input'!E20/1000 -> -31.546 | F12: ='P&L Input'!F20/1000 -> -57.837 | G12: ='P&L Input'!G20/1000 -> -110
B13: Minority interest | C13: ='P&L Input'!C22/1000 -> 0 | D13: ='P&L Input'!D22/1000 -> 98.132 | E13: ='P&L Input'!E22/1000 -> 279.178 | F13: ='P&L Input'!F22/1000 -> 86.491 | G13: ='P&L Input'!G22/1000 -> -87
B14: Net Income | C14: =SUM(C11:C13) -> -888.663 | D14: =SUM(D11:D13) -> -674.914 | E14: =SUM(E11:E13) -> -1961.4 | F14: =SUM(F11:F13) -> -976.091 | G14: =SUM(G11:G13) -> -862 | H14: =SUM(H11:H13) -> 2268.1419 | I14: =SUM(I11:I13) -> 2622.593 | J14: =SUM(J11:J13) -> 3320.4859 | ... Q14: =SUM(Q11:Q13) -> 5945.983
B16: Check
B17: Net income | C17: ='P&L Input'!C23/1000 -> -888.663 | D17: ='P&L Input'!D23/1000 -> -674.914 | E17: ='P&L Input'!E23/1000 -> -1961.4 | F17: ='P&L Input'!F23/1000 -> -976.091 | G17: ='P&L Input'!G23/1000 -> -862
C18: =C14-C17 -> 0 | D18: =D14-D17 -> 0 | E18: =E14-E17 -> 0 | F18: =F14-F17 -> 0 | G18: =G14-G17 -> 0

Sheet Balance Sheet
B1: Balance Sheet
C3: Tesla BS (in mln $)
B4: ($ in million) | C4: 31Dec2015 Act | D4: 31Dec2016 Act | E4: 31Dec2017 Act | F4: 31Dec2018 Act | G4: 31Dec2019 Act | H4: 31Dec2020 Fcst | I4: 31Dec2021 Fcst | J4: 31Dec2022 Fcst | K4: 31Dec2023 Fcst | L4: 31Dec2024 Fcst | M4: 31Dec2025 Fcst | N4: 31Dec2026 Fcst | O4: 31Dec2027 Fcst | P4: 31Dec2028 Fcst | Q4: 31Dec2029 Fcst | S4: Assumption
B5: Cash | C5: =('Balance Sheet Input'!C4)/1000 -> 1196.908 | D5: =('Balance Sheet Input'!D4)/1000 -> 3393.216 | E5: =('Balance Sheet Input'!E4)/1000 -> 3367.914 | F5: =('Balance Sheet Input'!F4)/1000 -> 3685.618 | G5: =('Balance Sheet Input'!G4)/1000 -> 6268 | S5: Cash flow sheet
B6: Restricted cash and securities | C6: =+'Balance Sheet Input'!C5/1000 -> 22.628 | D6: =+'Balance Sheet Input'!D5/1000 -> 105.519 | E6: =+'Balance Sheet Input'!E5/1000 -> 155.323 | F6: =+'Balance Sheet Input'!F5/1000 -> 192.551 | G6: =+'Balance Sheet Input'!G5/1000 -> 246 | H6: =$G$6 -> 246 | I6: =$G$6 -> 246 | J6: =$G$6 -> 246 | K6: =$G$6 -> 246 | L6: =$G$6 -> 246 | M6: =$G$6 -> 246 | N6: =$G$6 -> 246 | O6: =$G$6 -> 246 | ... Q6: =$G$6 -> 246 | S6: Stays flat
B7: Trade receivables | C7: =('Balance Sheet Input'!C6)/1000 -> 168.965 | D7: =('Balance Sheet Input'!D6)/1000 -> 499.142 | E7: =('Balance Sheet Input'!E6)/1000 -> 515.381 | F7: =('Balance Sheet Input'!F6)/1000 -> 949.022 | G7: =('Balance Sheet Input'!G6)/1000 -> 1324 | H7: ='Working capital'!H5 -> 1920.1572 | I7: ='Working capital'!I5 -> 2546.4248 | J7: ='Working capital'!J5 -> 3458.4184 | K7: ='Working capital'!K5 -> 4447.3127 | L7: ='Working capital'!L5 -> 5079.7666 | M7: ='Working capital'!M5 -> 5437.6679 | N7: ='Working capital'!N5 -> 5788.8771 | O7: ='Working capital'!O5 -> 6145.7305 | ... Q7: ='Working capital'!Q5 -> 6707.6658 | S7: Working capital sheet
B8: Inventory | C8: =('Balance Sheet Input'!C7)/1000 -> 1277.838 | D8: =('Balance Sheet Input'!D7)/1000 -> 2067.454 | E8: =('Balance Sheet Input'!E7)/1000 -> 2263.537 | F8: =('Balance Sheet Input'!F7)/1000 -> 3113.446 | G8: =('Balance Sheet Input'!G7)/1000 -> 3552 | H8: ='Working capital'!H6 -> 8353.4109 | I8: ='Working capital'!I6 -> 11184.361 | J8: ='Working capital'!J6 -> 15256.687 | K8: ='Working capital'!K6 -> 19680.056 | L8: ='Working capital'!L6 -> 22463.324 | M8: ='Working capital'!M6 -> 24063.439 | N8: ='Working capital'!N6 -> 25630.801 | O8: ='Working capital'!O6 -> 27225.903 | ... Q8: ='Working capital'!Q6 -> 29727.142 | S8: Working capital sheet
B9: Prepaid expenses | C9: =('Balance Sheet Input'!C8)/1000 -> 115.667 | D9: =('Balance Sheet Input'!D8)/1000 -> 194.465 | E9: =('Balance Sheet Input'!E8)/1000 -> 268.365 | F9: =('Balance Sheet Input'!F8)/1000 -> 365.671 | G9: =('Balance Sheet Input'!G8)/1000 -> 713 | H9: =H10*('P&L'!H$5) -> 866.91579 | I9: =I10*('P&L'!I$5) -> 1149.6642 | J9: =J10*('P&L'!J$5) -> 1561.4126 | K9: =K10*('P&L'!K$5) -> 2007.8802 | L9: =L10*('P&L'!L$5) -> 2293.4215 | M9: =M10*('P&L'!M$5) -> 2455.0074 | N9: =N10*('P&L'!N$5) -> 2613.572 | O9: =O10*('P&L'!O$5) -> 2774.6847 | ... Q9: =Q10*('P&L'!Q$5) -> 3028.3882 | S9: Grows as a % of revenues
B10: as a % of revenues | C10: =C9/('P&L'!C$5) -> 0.028587811 | D10: =D9/('P&L'!D$5) -> 0.02778019 | E10: =E9/('P&L'!E$5) -> 0.022822577 | F10: =F9/('P&L'!F$5) -> 0.017038648 | G10: =G9/('P&L'!G$5) -> 0.029009683 | H10: =AVERAGE($F$10:$G$10) -> 0.023024166 | I10: =AVERAGE($F$10:$G$10) -> 0.023024166 | J10: =AVERAGE($F$10:$G$10) -> 0.023024166 | K10: =AVERAGE($F$10:$G$10) -> 0.023024166 | L10: =AVERAGE($F$10:$G$10) -> 0.023024166 | M10: =AVERAGE($F$10:$G$10) -> 0.023024166 | N10: =AVERAGE($F$10:$G$10) -> 0.023024166 | O10: =AVERAGE($F$10:$G$10) -> 0.023024166 | ... Q10: =AVERAGE($F$10:$G$10) -> 0.023024166
B11: Operating lease vehicles | C11: =('Balance Sheet Input'!C10)/1000+'Balance Sheet Input'!C13/1000 -> 1791.403 | D11: =('Balance Sheet Input'!D10)/1000+'Balance Sheet Input'!D13/1000 -> 3134.08 | E11: =('Balance Sheet Input'!E10)/1000+'Balance Sheet Input'!E13/1000 -> 4116.604 | F11: =('Balance Sheet Input'!F10)/1000+'Balance Sheet Input'!F13/1000 -> 2089.758 | G11: =('Balance Sheet Input'!G10)/1000+'Balance Sheet Input'!G13/1000 -> 3665 | H11: =$G$11 -> 3665 | I11: =$G$11 -> 3665 | J11: =$G$11 -> 3665 | K11: =$G$11 -> 3665 | L11: =$G$11 -> 3665 | M11: =$G$11 -> 3665 | N11: =$G$11 -> 3665 | O11: =$G$11 -> 3665 | ... Q11: =$G$11 -> 3665 | S11: Stays flat
B12: Solar energy systems leased | C12: =('Balance Sheet Input'!C11)/1000 -> 0 | D12: =('Balance Sheet Input'!D11)/1000 -> 5919.88 | E12: =('Balance Sheet Input'!E11)/1000 -> 6347.49 | F12: =('Balance Sheet Input'!F11)/1000 -> 6271.396 | G12: =('Balance Sheet Input'!G11)/1000 -> 6138 | H12: =$G$12 -> 6138 | I12: =$G$12 -> 6138 | J12: =$G$12 -> 6138 | K12: =$G$12 -> 6138 | L12: =$G$12 -> 6138 | M12: =$G$12 -> 6138 | N12: =$G$12 -> 6138 | O12: =$G$12 -> 6138 | ... Q12: =$G$12 -> 6138 | S12: Stays flat
B13: PP&E | C13: =('Balance Sheet Input'!C12)/1000 -> 3403.334 | D13: =('Balance Sheet Input'!D12)/1000 -> 5982.957 | E13: =('Balance Sheet Input'!E12)/1000 -> 10027.522 | F13: =('Balance Sheet Input'!F12)/1000 -> 11330.077 | G13: =('Balance Sheet Input'!G12)/1000 -> 10396 | H13: ='PP&E'!H10 -> 11620.915 | I13: ='PP&E'!I10 -> 12861.036 | J13: ='PP&E'!J10 -> 14090.027 | K13: ='PP&E'!K10 -> 15275.45 | L13: ='PP&E'!L10 -> 16378.07 | M13: ='PP&E'!M10 -> 17351.159 | N13: ='PP&E'!N10 -> 18139.816 | O13: ='PP&E'!O10 -> 18680.316 | ... Q13: ='PP&E'!Q10 -> 18714.345 | S13: PP&E sheet
B14: Intangible assets | C14: =('Balance Sheet Input'!C14)/1000 -> 12.816 | D14: =('Balance Sheet Input'!D14)/1000 -> 376.145 | E14: =('Balance Sheet Input'!E14)/1000 -> 361.502 | F14: =('Balance Sheet Input'!F14)/1000 -> 282.492 | G14: =('Balance Sheet Input'!G14)/1000 -> 339 | H14: =$G$14 -> 339 | I14: =$G$14 -> 339 | J14: =$G$14 -> 339 | K14: =$G$14 -> 339 | L14: =$G$14 -> 339 | M14: =$G$14 -> 339 | N14: =$G$14 -> 339 | O14: =$G$14 -> 339 | ... Q14: =$G$14 -> 339 | S14: Stays flat
B15: Other assets | C15: =('Balance Sheet Input'!C17+'Balance Sheet Input'!C16+'Balance Sheet Input'!C15)/1000 -> 78.38 | D15: =('Balance Sheet Input'!D17+'Balance Sheet Input'!D16+'Balance Sheet Input'!D15)/1000 -> 991.218 | E15: =('Balance Sheet Input'!E17+'Balance Sheet Input'!E16+'Balance Sheet Input'!E15)/1000 -> 1231.734 | F15: =('Balance Sheet Input'!F17+'Balance Sheet Input'!F16+'Balance Sheet Input'!F15)/1000 -> 1459.583 | G15: =('Balance Sheet Input'!G17+'Balance Sheet Input'!G16+'Balance Sheet Input'!G15)/1000 -> 1668 | H15: =H16*('P&L'!H$5) -> 2558.0246 | I15: =I16*('P&L'!I$5) -> 3392.3355 | J15: =J16*('P&L'!J$5) -> 4607.2891 | K15: =K16*('P&L'!K$5) -> 5924.6896 | L15: =L16*('P&L'!L$5) -> 6767.2417 | M15: =M16*('P&L'!M$5) -> 7244.0362 | N15: =N16*('P&L'!N$5) -> 7711.9155 | O15: =O16*('P&L'!O$5) -> 8187.3139 | ... Q15: =Q16*('P&L'!Q$5) -> 8935.9215 | S15: Grows as a % of revenues
B16: as a % of revenues | C16: =C15/('P&L'!C$5) -> 0.0193721 | D16: =D15/('P&L'!D$5) -> 0.1415999 | E16: =E15/('P&L'!E$5) -> 0.10475041 | F16: =F15/('P&L'!F$5) -> 0.068010101 | G16: =G15/('P&L'!G$5) -> 0.067865571 | H16: =AVERAGE($F$16:$G$16) -> 0.067937836 | I16: =AVERAGE($F$16:$G$16) -> 0.067937836 | J16: =AVERAGE($F$16:$G$16) -> 0.067937836 | K16: =AVERAGE($F$16:$G$16) -> 0.067937836 | L16: =AVERAGE($F$16:$G$16) -> 0.067937836 | M16: =AVERAGE($F$16:$G$16) -> 0.067937836 | N16: =AVERAGE($F$16:$G$16) -> 0.067937836 | O16: =AVERAGE($F$16:$G$16) -> 0.067937836 | ... Q16: =AVERAGE($F$16:$G$16) -> 0.067937836
B17: Total assets | C17: =C5+C6+C7+C8+C9+C11+C13+C15+C12+C14 -> 8067.939 | D17: =D5+D6+D7+D8+D9+D11+D13+D15+D12+D14 -> 22664.076 | E17: =E5+E6+E7+E8+E9+E11+E13+E15+E12+E14 -> 28655.372 | F17: =F5+F6+F7+F8+F9+F11+F13+F15+F12+F14 -> 29739.614 | G17: =G5+G6+G7+G8+G9+G11+G13+G15+G12+G14 -> 34309 | H17: =H5+H6+H7+H8+H9+H11+H13+H15+H12+H14 -> 35707.424 | I17: =I5+I6+I7+I8+I9+I11+I13+I15+I12+I14 -> 41521.821 | J17: =J5+J6+J7+J8+J9+J11+J13+J15+J12+J14 -> 49361.834 | ... Q17: =Q5+Q6+Q7+Q8+Q9+Q11+Q13+Q15+Q12+Q14 -> 77501.462
B19: Accounts payable | C19: ='Balance Sheet Input'!C19/1000 -> 916.148 | D19: ='Balance Sheet Input'!D19/1000 -> 1860.341 | E19: ='Balance Sheet Input'!E19/1000 -> 2390.25 | F19: ='Balance Sheet Input'!F19/1000 -> 3404.451 | G19: ='Balance Sheet Input'!G19/1000 -> 3771 | H19: ='Working capital'!H7 -> 7666.976 | I19: ='Working capital'!I7 -> 10265.295 | J19: ='Working capital'!J7 -> 14002.981 | K19: ='Working capital'!K7 -> 18062.863 | L19: ='Working capital'!L7 -> 20617.418 | M19: ='Working capital'!M7 -> 22086.045 | N19: ='Working capital'!N7 -> 23524.61 | O19: ='Working capital'!O7 -> 24988.636 | ... Q19: ='Working capital'!Q7 -> 27284.338 | S19: Working capital sheet
B20: Accrued liabilities | C20: ='Balance Sheet Input'!C20/1000 -> 422.798 | D20: ='Balance Sheet Input'!D20/1000 -> 1210.028 | E20: ='Balance Sheet Input'!E20/1000 -> 1731.366 | F20: ='Balance Sheet Input'!F20/1000 -> 2094.253 | G20: ='Balance Sheet Input'!G20/1000 -> 2905 | H20: =H21*('P&L'!H$5) -> 4062.2838 | I20: =I21*('P&L'!I$5) -> 5387.2154 | J20: =J21*('P&L'!J$5) -> 7316.6287 | K20: =K21*('P&L'!K$5) -> 9408.7331 | L20: =L21*('P&L'!L$5) -> 10746.752 | M20: =M21*('P&L'!M$5) -> 11503.928 | N20: =N21*('P&L'!N$5) -> 12246.946 | O20: =O21*('P&L'!O$5) -> 13001.905 | ... Q20: =Q21*('P&L'!Q$5) -> 14190.735 | S20: Grows as a % of revenues
B21: as a % of revenues | C21: =C20/('P&L'!C$5) -> 0.10449713 | D21: =D20/('P&L'!D$5) -> 0.17285788 | E21: =E20/('P&L'!E$5) -> 0.14724064 | F21: =F20/('P&L'!F$5) -> 0.097582911 | G21: =G20/('P&L'!G$5) -> 0.11819513 | H21: =AVERAGE($F$21:$G$21) -> 0.10788902 | I21: =AVERAGE($F$21:$G$21) -> 0.10788902 | J21: =AVERAGE($F$21:$G$21) -> 0.10788902 | K21: =AVERAGE($F$21:$G$21) -> 0.10788902 | L21: =AVERAGE($F$21:$G$21) -> 0.10788902 | M21: =AVERAGE($F$21:$G$21) -> 0.10788902 | N21: =AVERAGE($F$21:$G$21) -> 0.10788902 | O21: =AVERAGE($F$21:$G$21) -> 0.10788902 | ... Q21: =AVERAGE($F$21:$G$21) -> 0.10788902
B22: Deferred revenue | C22: ='Balance Sheet Input'!C21/1000 -> 423.961 | D22: ='Balance Sheet Input'!D21/1000 -> 763.126 | E22: ='Balance Sheet Input'!E21/1000 -> 1015.253 | F22: ='Balance Sheet Input'!F21/1000 -> 630.292 | G22: ='Balance Sheet Input'!G21/1000 -> 1163 | H22: =H23*('P&L'!H$5) -> 1443.7364 | I22: =I23*('P&L'!I$5) -> 1914.6173 | J22: =J23*('P&L'!J$5) -> 2600.3311 | K22: =K23*('P&L'!K$5) -> 3343.8654 | L22: =L23*('P&L'!L$5) -> 3819.3976 | M22: =M23*('P&L'!M$5) -> 4088.4981 | N22: =N23*('P&L'!N$5) -> 4352.5669 | O22: =O23*('P&L'!O$5) -> 4620.8794 | ... Q22: =Q23*('P&L'!Q$5) -> 5043.3898 | S22: Grows as a % of revenues
B23: as a % of revenues | C23: =C22/('P&L'!C$5) -> 0.10478457 | D23: =D22/('P&L'!D$5) -> 0.10901594 | E23: =E22/('P&L'!E$5) -> 0.086340207 | F23: =F22/('P&L'!F$5) -> 0.029368815 | G23: =G22/('P&L'!G$5) -> 0.04731874 | H23: =AVERAGE($F$23:$G$23) -> 0.038343777 | I23: =AVERAGE($F$23:$G$23) -> 0.038343777 | J23: =AVERAGE($F$23:$G$23) -> 0.038343777 | K23: =AVERAGE($F$23:$G$23) -> 0.038343777 | L23: =AVERAGE($F$23:$G$23) -> 0.038343777 | M23: =AVERAGE($F$23:$G$23) -> 0.038343777 | N23: =AVERAGE($F$23:$G$23) -> 0.038343777 | O23: =AVERAGE($F$23:$G$23) -> 0.038343777 | ... Q23: =AVERAGE($F$23:$G$23) -> 0.038343777
B24: Resale value guarantees | C24: ='Balance Sheet Input'!C22/1000 -> 136.831 | D24: ='Balance Sheet Input'!D22/1000 -> 179.504 | E24: ='Balance Sheet Input'!E22/1000 -> 787.333 | F24: ='Balance Sheet Input'!F22/1000 -> 502.84 | G24: ='Balance Sheet Input'!G22/1000 -> 317 | H24: =H25*('P&L'!H$5) -> 683.91552 | I24: =I25*('P&L'!I$5) -> 906.97755 | J24: =J25*('P&L'!J$5) -> 1231.8085 | K24: =K25*('P&L'!K$5) -> 1584.0298 | L24: =L25*('P&L'!L$5) -> 1809.2952 | M24: =M25*('P&L'!M$5) -> 1936.7714 | N24: =N25*('P&L'!N$5) -> 2061.864 | O24: =O25*('P&L'!O$5) -> 2188.9669 | ... Q24: =Q25*('P&L'!Q$5) -> 2389.1152 | S24: Grows as a % of revenues
B25: as a % of revenues | C25: =C24/('P&L'!C$5) -> 0.033818624 | D25: =D24/('P&L'!D$5) -> 0.025642945 | E25: =E24/('P&L'!E$5) -> 0.066957196 | F25: =F24/('P&L'!F$5) -> 0.023430116 | G25: =G24/('P&L'!G$5) -> 0.012897713 | H25: =AVERAGE($F$25:$G$25) -> 0.018163915 | I25: =AVERAGE($F$25:$G$25) -> 0.018163915 | J25: =AVERAGE($F$25:$G$25) -> 0.018163915 | K25: =AVERAGE($F$25:$G$25) -> 0.018163915 | L25: =AVERAGE($F$25:$G$25) -> 0.018163915 | M25: =AVERAGE($F$25:$G$25) -> 0.018163915 | N25: =AVERAGE($F$25:$G$25) -> 0.018163915 | O25: =AVERAGE($F$25:$G$25) -> 0.018163915 | ... Q25: =AVERAGE($F$25:$G$25) -> 0.018163915
B26: Customer deposits | C26: ='Balance Sheet Input'!C23/1000 -> 283.37 | D26: ='Balance Sheet Input'!D23/1000 -> 663.859 | E26: ='Balance Sheet Input'!E23/1000 -> 853.919 | F26: ='Balance Sheet Input'!F23/1000 -> 792.601 | G26: ='Balance Sheet Input'!G23/1000 -> 726 | H26: =H27*('P&L'!H$5) -> 1251.3843 | I26: =I27*('P&L'!I$5) -> 1659.5287 | J26: =J27*('P&L'!J$5) -> 2253.8834 | K26: =K27*('P&L'!K$5) -> 2898.355 | L26: =L27*('P&L'!L$5) -> 3310.531 | M26: =M27*('P&L'!M$5) -> 3543.7787 | N26: =N27*('P&L'!N$5) -> 3772.665 | O26: =O27*('P&L'!O$5) -> 4005.2296 | ... Q26: =Q27*('P&L'!Q$5) -> 4371.4481 | S26: Grows as a % of revenues
B27: as a % of revenues | C27: =C26/('P&L'!C$5) -> 0.070036641 | D27: =D26/('P&L'!D$5) -> 0.094835212 | E27: =E26/('P&L'!E$5) -> 0.072619873 | F27: =F26/('P&L'!F$5) -> 0.036931695 | G27: =G26/('P&L'!G$5) -> 0.029538612 | H27: =AVERAGE($F$27:$G$27) -> 0.033235153 | I27: =AVERAGE($F$27:$G$27) -> 0.033235153 | J27: =AVERAGE($F$27:$G$27) -> 0.033235153 | K27: =AVERAGE($F$27:$G$27) -> 0.033235153 | L27: =AVERAGE($F$27:$G$27) -> 0.033235153 | M27: =AVERAGE($F$27:$G$27) -> 0.033235153 | N27: =AVERAGE($F$27:$G$27) -> 0.033235153 | O27: =AVERAGE($F$27:$G$27) -> 0.033235153 | ... Q27: =AVERAGE($F$27:$G$27) -> 0.033235153
B28: Long-term debt | C28: =('Balance Sheet Input'!C24+'Balance Sheet Input'!C29)/1000 -> 2649.02 | D28: =('Balance Sheet Input'!D24+'Balance Sheet Input'!D29)/1000 -> 6844.26 | E28: =('Balance Sheet Input'!E24+'Balance Sheet Input'!E29)/1000 -> 10212.249 | F28: =('Balance Sheet Input'!F24+'Balance Sheet Input'!F29)/1000 -> 11971.371 | G28: =('Balance Sheet Input'!G24+'Balance Sheet Input'!G29)/1000 -> 13419 | H28: =G28+Financing!H19 -> 13419 | I28: =H28+Financing!I19 -> 13419 | J28: =I28+Financing!J19 -> 13419 | K28: =J28+Financing!K19 -> 13419 | L28: =K28+Financing!L19 -> 13419 | M28: =L28+Financing!M19 -> 13419 | N28: =M28+Financing!N19 -> 13419 | O28: =N28+Financing!O19 -> 13419 | ... Q28: =P28+Financing!Q19 -> 13419 | S28: Financing sheet
B29: Other liabilities | C29: =('Balance Sheet Input'!C30+'Balance Sheet Input'!C26)/1000 -> 2152.107 | D29: =('Balance Sheet Input'!D30+'Balance Sheet Input'!D26)/1000 -> 5604.872 | E29: =('Balance Sheet Input'!E30+'Balance Sheet Input'!E26)/1000 -> 6430.414 | F29: =('Balance Sheet Input'!F30+'Balance Sheet Input'!F26)/1000 -> 4586.166 | G29: =('Balance Sheet Input'!G30+'Balance Sheet Input'!G26)/1000 -> 4541 | H29: =H30*('P&L'!H$5) -> 7501.3758 | I29: =I30*('P&L'!I$5) -> 9947.9822 | J29: =J30*('P&L'!J$5) -> 13510.819 | K29: =K30*('P&L'!K$5) -> 17374.08 | L29: =L30*('P&L'!L$5) -> 19844.853 | M29: =M30*('P&L'!M$5) -> 21243.047 | N29: =N30*('P&L'!N$5) -> 22615.098 | O29: =O30*('P&L'!O$5) -> 24009.198 | ... Q29: =Q30*('P&L'!Q$5) -> 26204.48 | S29: Grows as a % of revenues
B30: as a % of revenues | C30: =C29/('P&L'!C$5) -> 0.5319065 | D30: =D29/('P&L'!D$5) -> 0.8006809 | E30: =E29/('P&L'!E$5) -> 0.54686199 | F30: =F29/('P&L'!F$5) -> 0.21369502 | G30: =G29/('P&L'!G$5) -> 0.18475873 | H30: =AVERAGE($F$30:$G$30) -> 0.19922687 | I30: =AVERAGE($F$30:$G$30) -> 0.19922687 | J30: =AVERAGE($F$30:$G$30) -> 0.19922687 | K30: =AVERAGE($F$30:$G$30) -> 0.19922687 | L30: =AVERAGE($F$30:$G$30) -> 0.19922687 | M30: =AVERAGE($F$30:$G$30) -> 0.19922687 | N30: =AVERAGE($F$30:$G$30) -> 0.19922687 | O30: =AVERAGE($F$30:$G$30) -> 0.19922687 | ... Q30: =AVERAGE($F$30:$G$30) -> 0.19922687
B31: Total liabilities | C31: =C19+C20+C22+C24+C26+C28+C29 -> 6984.235 | D31: =D19+D20+D22+D24+D26+D28+D29 -> 17125.99 | E31: =E19+E20+E22+E24+E26+E28+E29 -> 23420.784 | F31: =F19+F20+F22+F24+F26+F28+F29 -> 23981.974 | G31: =G19+G20+G22+G24+G26+G28+G29 -> 26842 | H31: =H19+H20+H22+H24+H26+H28+H29 -> 36028.672 | I31: =I19+I20+I22+I24+I26+I28+I29 -> 43500.616 | J31: =J19+J20+J22+J24+J26+J28+J29 -> 54335.451 | ... Q31: =Q19+Q20+Q22+Q24+Q26+Q28+Q29 -> 92902.506
B32: Equity | C32: =('Balance Sheet Input'!C33+'Balance Sheet Input'!C32)/1000 -> 1083.704 | D32: =('Balance Sheet Input'!D33+'Balance Sheet Input'!D32)/1000 -> 5538.086 | E32: =('Balance Sheet Input'!E33+'Balance Sheet Input'!E32)/1000 -> 5234.588 | F32: =('Balance Sheet Input'!F33+'Balance Sheet Input'!F32)/1000 -> 5757.64 | G32: =('Balance Sheet Input'!G33+'Balance Sheet Input'!G32)/1000 -> 7467 | H32: =G32+'P&L'!H14+Financing!H20 -> 9735.1419 | I32: =H32+'P&L'!I14+Financing!I20 -> 12357.735 | J32: =I32+'P&L'!J14+Financing!J20 -> 15678.221 | K32: =J32+'P&L'!K14+Financing!K20 -> 19727.727 | L32: =K32+'P&L'!L14+Financing!L20 -> 24409.003 | M32: =L32+'P&L'!M14+Financing!M20 -> 29357 | N32: =M32+'P&L'!N14+Financing!N20 -> 34576.988 | O32: =N32+'P&L'!O14+Financing!O20 -> 40064.101 | ... Q32: =P32+'P&L'!Q14+Financing!Q20 -> 51747.374
B34: Total liabilities & equity | C34: =C31+C32 -> 8067.939 | D34: =D31+D32 -> 22664.076 | E34: =E31+E32 -> 28655.372 | F34: =F31+F32 -> 29739.614 | G34: =G31+G32 -> 34309 | H34: =H31+H32 -> 45763.814 | I34: =I31+I32 -> 55858.351 | J34: =J31+J32 -> 70013.672 | ... Q34: =Q31+Q32 -> 144649.88
B36: Check | C36: =C17-C34 -> 0 | D36: =D17-D34 -> 0 | E36: =E17-E34 -> 0 | F36: =F17-F34 -> 0 | G36: =G17-G34 -> 0

Sheet Cash Flow
B1: Cash Flow
C3: Tesla Cash Flow (in mln $)
B4: ($ in million) | C4: 2015 Act | D4: 2016 Act | E4: 2017 Act | F4: 2018 Act | G4: 2019 Act | H4: 2020 Fcst | I4: 2021 Fcst | J4: 2022 Fcst | K4: 2023 Fcst | L4: 2024 Fcst | M4: 2025 Fcst | N4: 2026 Fcst | O4: 2027 Fcst | P4: 2028 Fcst | Q4: 2029 Fcst
B5: EBIT | D5: ='P&L'!D9 -> -667.34 | E5: ='P&L'!E9 -> -1632.086 | F5: ='P&L'!F9 -> -388.073 | G5: ='P&L'!G9 -> -69 | H5: ='P&L'!H9 -> 2268.1419 | I5: ='P&L'!I9 -> 2622.593 | J5: ='P&L'!J9 -> 3320.4859 | K5: ='P&L'!K9 -> 4049.506 | ... Q5: ='P&L'!Q9 -> 5945.983
B6: =CONCATENATE("Operating taxes (",(Drivers!$C$12*100),"%)") -> Operating taxes (21%) | D6: ='P&L'!D12 -> -26.698 | E6: ='P&L'!E12 -> -31.546 | F6: ='P&L'!F12 -> -57.837 | G6: ='P&L'!G12 -> -110 | H6: =IF(H5*Drivers!$C$12>0,-H5*Drivers!$C$12,0) -> -476.30979 | I6: =IF(I5*Drivers!$C$12>0,-I5*Drivers!$C$12,0) -> -550.74453 | J6: =IF(J5*Drivers!$C$12>0,-J5*Drivers!$C$12,0) -> -697.30203 | K6: =IF(K5*Drivers!$C$12>0,-K5*Drivers!$C$12,0) -> -850.39626 | L6: =IF(L5*Drivers!$C$12>0,-L5*Drivers!$C$12,0) -> -983.06793 | M6: =IF(M5*Drivers!$C$12>0,-M5*Drivers!$C$12,0) -> -1039.0794 | N6: =IF(N5*Drivers!$C$12>0,-N5*Drivers!$C$12,0) -> -1096.1976 | O6: =IF(O5*Drivers!$C$12>0,-O5*Drivers!$C$12,0) -> -1152.2937 | ... Q6: =IF(Q5*Drivers!$C$12>0,-Q5*Drivers!$C$12,0) -> -1248.6564
B7: NOPAT | D7: =SUM(D5:D6) -> -694.038 | E7: =SUM(E5:E6) -> -1663.632 | F7: =SUM(F5:F6) -> -445.91 | G7: =SUM(G5:G6) -> -179 | H7: =SUM(H5:H6) -> 1791.8321 | I7: =SUM(I5:I6) -> 2071.8485 | J7: =SUM(J5:J6) -> 2623.1838 | K7: =SUM(K5:K6) -> 3199.1097 | ... Q7: =SUM(Q5:Q6) -> 4697.3266
B8: Add-back D&A | D8: =-'PP&E'!D9 -> 947 | E8: =-'PP&E'!E9 -> 1636 | F8: =-'PP&E'!F9 -> 1901 | G8: =-'PP&E'!G9 -> 2154 | H8: =-'PP&E'!H9 -> 1291.2128 | I8: =-'PP&E'!I9 -> 1572.472 | J8: =-'PP&E'!J9 -> 1883.7457 | K8: =-'PP&E'!K9 -> 2224.7645 | ... Q8: =-'PP&E'!Q9 -> 4759.3913
B9: Gross Cash Flow | D9: =SUM(D7:D8) -> 252.962 | E9: =SUM(E7:E8) -> -27.632 | F9: =SUM(F7:F8) -> 1455.09 | G9: =SUM(G7:G8) -> 1975 | H9: =SUM(H7:H8) -> 3083.0449 | I9: =SUM(I7:I8) -> 3644.3205 | J9: =SUM(J7:J8) -> 4506.9296 | K9: =SUM(K7:K8) -> 5423.8742 | ... Q9: =SUM(Q7:Q8) -> 9456.7179
B11: Trade receivables | D11: =-('Balance Sheet'!D7-'Balance Sheet'!C7) -> -330.177 | E11: =-('Balance Sheet'!E7-'Balance Sheet'!D7) -> -16.239 | F11: =-('Balance Sheet'!F7-'Balance Sheet'!E7) -> -433.641 | G11: =-('Balance Sheet'!G7-'Balance Sheet'!F7) -> -374.978
B12: Inventory | D12: =-('Balance Sheet'!D8-'Balance Sheet'!C8) -> -789.616 | E12: =-('Balance Sheet'!E8-'Balance Sheet'!D8) -> -196.083 | F12: =-('Balance Sheet'!F8-'Balance Sheet'!E8) -> -849.909 | G12: =-('Balance Sheet'!G8-'Balance Sheet'!F8) -> -438.554
B13: Accounts payable | D13: ='Balance Sheet'!D19-'Balance Sheet'!C19 -> 944.193 | E13: ='Balance Sheet'!E19-'Balance Sheet'!D19 -> 529.909 | F13: ='Balance Sheet'!F19-'Balance Sheet'!E19 -> 1014.201 | G13: ='Balance Sheet'!G19-'Balance Sheet'!F19 -> 366.549
B14: Investments in Working Capital | D14: =SUM(D11:D13) -> -175.6 | E14: =SUM(E11:E13) -> 317.587 | F14: =SUM(F11:F13) -> -269.349 | G14: =SUM(G11:G13) -> -446.983 | H14: =SUM(H11:H13) -> 0 | I14: =SUM(I11:I13) -> 0 | J14: =SUM(J11:J13) -> 0 | K14: =SUM(K11:K13) -> 0 | ... Q14: =SUM(Q11:Q13) -> 0
B16: Capex | D16: =-'PP&E'!D8 -> -3526.623 | E16: =-'PP&E'!E8 -> -5680.565 | F16: =-'PP&E'!F8 -> -3203.555 | G16: =-'PP&E'!G8 -> -1219.923
B17: Other assets | D17: =-('Balance Sheet'!D6-'Balance Sheet'!C6)-('Balance Sheet'!D9-'Balance Sheet'!C9)-('Balance Sheet'!D11-'Balance Sheet'!C11)-('Balance Sheet'!D12-'Balance Sheet'!C12)-('Balance Sheet'!D14-'Balance Sheet'!C14)-('Balance Sheet'!D15-'Balance Sheet'!C15) -> -8700.413 | E17: =-('Balance Sheet'!E6-'Balance Sheet'!D6)-('Balance Sheet'!E9-'Balance Sheet'!D9)-('Balance Sheet'!E11-'Balance Sheet'!D11)-('Balance Sheet'!E12-'Balance Sheet'!D12)-('Balance Sheet'!E14-'Balance Sheet'!D14)-('Balance Sheet'!E15-'Balance Sheet'!D15) -> -1759.711 | F17: =-('Balance Sheet'!F6-'Balance Sheet'!E6)-('Balance Sheet'!F9-'Balance Sheet'!E9)-('Balance Sheet'!F11-'Balance Sheet'!E11)-('Balance Sheet'!F12-'Balance Sheet'!E12)-('Balance Sheet'!F14-'Balance Sheet'!E14)-('Balance Sheet'!F15-'Balance Sheet'!E15) -> 1819.567 | G17: =-('Balance Sheet'!G6-'Balance Sheet'!F6)-('Balance Sheet'!G9-'Balance Sheet'!F9)-('Balance Sheet'!G11-'Balance Sheet'!F11)-('Balance Sheet'!G12-'Balance Sheet'!F12)-('Balance Sheet'!G14-'Balance Sheet'!F14)-('Balance Sheet'!G15-'Balance Sheet'!F15) -> -2107.549
B18: Other liabilties | D18: =('Balance Sheet'!D20-'Balance Sheet'!C20)+('Balance Sheet'!D22-'Balance Sheet'!C22)+('Balance Sheet'!D24-'Balance Sheet'!C24)+('Balance Sheet'!D26-'Balance Sheet'!C26)+('Balance Sheet'!D29-'Balance Sheet'!C29) -> 5002.322 | E18: =('Balance Sheet'!E20-'Balance Sheet'!D20)+('Balance Sheet'!E22-'Balance Sheet'!D22)+('Balance Sheet'!E24-'Balance Sheet'!D24)+('Balance Sheet'!E26-'Balance Sheet'!D26)+('Balance Sheet'!E29-'Balance Sheet'!D29) -> 2396.896 | F18: =('Balance Sheet'!F20-'Balance Sheet'!E20)+('Balance Sheet'!F22-'Balance Sheet'!E22)+('Balance Sheet'!F24-'Balance Sheet'!E24)+('Balance Sheet'!F26-'Balance Sheet'!E26)+('Balance Sheet'!F29-'Balance Sheet'!E29) -> -2212.133 | G18: =('Balance Sheet'!G20-'Balance Sheet'!F20)+('Balance Sheet'!G22-'Balance Sheet'!F22)+('Balance Sheet'!G24-'Balance Sheet'!F24)+('Balance Sheet'!G26-'Balance Sheet'!F26)+('Balance Sheet'!G29-'Balance Sheet'!F29) -> 1045.848
B20: Unlevered Free Cash Flow | D20: =D9+D14+D17+D18+D16 -> -7147.352 | E20: =E9+E14+E17+E18+E16 -> -4753.425 | F20: =F9+F14+F17+F18+F16 -> -2410.38 | G20: =G9+G14+G17+G18+G16 -> -753.607
B22: Interest expenses | D22: ='P&L'!D10 -> -79.008 | E22: ='P&L'!E10 -> -576.946 | F22: ='P&L'!F10 -> -616.672 | G22: ='P&L'!G10 -> -596
B23: Delta Financial liabilities | D23: ='Balance Sheet'!D28-'Balance Sheet'!C28 -> 4195.24 | E23: ='Balance Sheet'!E28-'Balance Sheet'!D28 -> 3367.989 | F23: ='Balance Sheet'!F28-'Balance Sheet'!E28 -> 1759.122 | G23: ='Balance Sheet'!G28-'Balance Sheet'!F28 -> 1447.629
B24: Delta equity/Other equity movements | D24: ='Balance Sheet'!D32-'Balance Sheet'!C32-'P&L'!D14 -> 5129.296 | E24: ='Balance Sheet'!E32-'Balance Sheet'!D32-'P&L'!E14 -> 1657.902 | F24: ='Balance Sheet'!F32-'Balance Sheet'!E32-'P&L'!F14 -> 1499.143 | G24: ='Balance Sheet'!G32-'Balance Sheet'!F32-'P&L'!G14 -> 2571.36
B25: Tax adjustment | D25: ='P&L'!D12-D6 -> 0 | E25: ='P&L'!E12-E6 -> 0 | F25: ='P&L'!F12-F6 -> 0 | G25: ='P&L'!G12-G6 -> 0
B26: Minority interest | D26: ='P&L'!D13 -> 98.132 | E26: ='P&L'!E13 -> 279.178 | F26: ='P&L'!F13 -> 86.491 | G26: ='P&L'!G13 -> -87
B28: Net Cash Flow | D28: =SUM(D20:D27) -> 2196.308 | E28: =SUM(E20:E27) -> -25.302 | F28: =SUM(F20:F27) -> 317.704 | G28: =SUM(G20:G27) -> 2582.382 | H28: =SUM(H20:H27) -> 0 | I28: =SUM(I20:I27) -> 0 | J28: =SUM(J20:J27) -> 0 | K28: =SUM(K20:K27) -> 0 | ... Q28: =SUM(Q20:Q27) -> 0
